{
"meta":{"test_sets":[],"test_metrics":[],"learn_metrics":[{"best_value":"Min","name":"RMSE"}],"launch_mode":"Train","parameters":"","iteration_count":1000,"learn_sets":["learn"],"name":"experiment"},
"iterations":[
{"learn":[14.61268541],"iteration":0,"passed_time":0.1353000715,"remaining_time":135.1647714},
{"learn":[14.23196558],"iteration":1,"passed_time":0.1367234637,"remaining_time":68.22500841},
{"learn":[13.86674177],"iteration":2,"passed_time":0.1380073106,"remaining_time":45.86442957},
{"learn":[13.49946468],"iteration":3,"passed_time":0.139340018,"remaining_time":34.69566448},
{"learn":[13.16661202],"iteration":4,"passed_time":0.1406157034,"remaining_time":27.98252498},
{"learn":[12.85632158],"iteration":5,"passed_time":0.1417998422,"remaining_time":23.49150719},
{"learn":[12.56784336],"iteration":6,"passed_time":0.142803533,"remaining_time":20.25770118},
{"learn":[12.31617801],"iteration":7,"passed_time":0.1439020946,"remaining_time":17.84385973},
{"learn":[12.01509946],"iteration":8,"passed_time":0.145046402,"remaining_time":15.97122048},
{"learn":[11.71512571],"iteration":9,"passed_time":0.1461564345,"remaining_time":14.46948702},
{"learn":[11.43264457],"iteration":10,"passed_time":0.1474399566,"remaining_time":13.25619246},
{"learn":[11.17973129],"iteration":11,"passed_time":0.1486802568,"remaining_time":12.24134114},
{"learn":[10.93746433],"iteration":12,"passed_time":0.1498783881,"remaining_time":11.37922839},
{"learn":[10.69387075],"iteration":13,"passed_time":0.1510853678,"remaining_time":10.64072662},
{"learn":[10.4615922],"iteration":14,"passed_time":0.1522832168,"remaining_time":9.999931234},
{"learn":[10.2299235],"iteration":15,"passed_time":0.1534748248,"remaining_time":9.438701724},
{"learn":[10.01419731],"iteration":16,"passed_time":0.1552372014,"remaining_time":8.976362882},
{"learn":[9.795856918],"iteration":17,"passed_time":0.1566875683,"remaining_time":8.548177337},
{"learn":[9.60040151],"iteration":18,"passed_time":0.1581729493,"remaining_time":8.166719119},
{"learn":[9.418664989],"iteration":19,"passed_time":0.1597254821,"remaining_time":7.826548622},
{"learn":[9.249278645],"iteration":20,"passed_time":0.1611081357,"remaining_time":7.510707851},
{"learn":[9.090113396],"iteration":21,"passed_time":0.1622121556,"remaining_time":7.211067645},
{"learn":[8.909548708],"iteration":22,"passed_time":0.1632993378,"remaining_time":6.93667187},
{"learn":[8.740140208],"iteration":23,"passed_time":0.1644557035,"remaining_time":6.687865275},
{"learn":[8.59377682],"iteration":24,"passed_time":0.1656991238,"remaining_time":6.462265826},
{"learn":[8.453885414],"iteration":25,"passed_time":0.1668929801,"remaining_time":6.252067792},
{"learn":[8.317732234],"iteration":26,"passed_time":0.1680725344,"remaining_time":6.056836147},
{"learn":[8.180896085],"iteration":27,"passed_time":0.1697992876,"remaining_time":5.894460983},
{"learn":[8.053220863],"iteration":28,"passed_time":0.1708653478,"remaining_time":5.721043198},
{"learn":[7.924234474],"iteration":29,"passed_time":0.1720502934,"remaining_time":5.562959487},
{"learn":[7.818879511],"iteration":30,"passed_time":0.1732678115,"remaining_time":5.416016431},
{"learn":[7.719346395],"iteration":31,"passed_time":0.1744810596,"remaining_time":5.278052053},
{"learn":[7.624163594],"iteration":32,"passed_time":0.1757007186,"remaining_time":5.14856348},
{"learn":[7.524952543],"iteration":33,"passed_time":0.1769002186,"remaining_time":5.026047386},
{"learn":[7.424464745],"iteration":34,"passed_time":0.178119082,"remaining_time":4.910997546},
{"learn":[7.327482321],"iteration":35,"passed_time":0.1794030959,"remaining_time":4.804016234},
{"learn":[7.238666841],"iteration":36,"passed_time":0.1805940483,"remaining_time":4.700326177},
{"learn":[7.158842395],"iteration":37,"passed_time":0.18173382,"remaining_time":4.600735126},
{"learn":[7.074348246],"iteration":38,"passed_time":0.1827871197,"remaining_time":4.504062103},
{"learn":[6.992269093],"iteration":39,"passed_time":0.1840487126,"remaining_time":4.417169102},
{"learn":[6.925219745],"iteration":40,"passed_time":0.1855422392,"remaining_time":4.339878229},
{"learn":[6.86013671],"iteration":41,"passed_time":0.1865581287,"remaining_time":4.255302078},
{"learn":[6.786739622],"iteration":42,"passed_time":0.187810428,"remaining_time":4.179873945},
{"learn":[6.73057926],"iteration":43,"passed_time":0.1890242717,"remaining_time":4.106981904},
{"learn":[6.666356486],"iteration":44,"passed_time":0.1902741,"remaining_time":4.038039233},
{"learn":[6.606182832],"iteration":45,"passed_time":0.1915349115,"remaining_time":3.972267513},
{"learn":[6.547854615],"iteration":46,"passed_time":0.1928073074,"remaining_time":3.909475828},
{"learn":[6.49240675],"iteration":47,"passed_time":0.1940029422,"remaining_time":3.84772502},
{"learn":[6.431317261],"iteration":48,"passed_time":0.1951974016,"remaining_time":3.78842304},
{"learn":[6.377586395],"iteration":49,"passed_time":0.196404365,"remaining_time":3.731682935},
{"learn":[6.327558015],"iteration":50,"passed_time":0.1976266072,"remaining_time":3.677404906},
{"learn":[6.282040317],"iteration":51,"passed_time":0.1988435122,"remaining_time":3.625070183},
{"learn":[6.237655841],"iteration":52,"passed_time":0.2015672025,"remaining_time":3.601587561},
{"learn":[6.192792003],"iteration":53,"passed_time":0.2031617429,"remaining_time":3.559092756},
{"learn":[6.150579347],"iteration":54,"passed_time":0.2046296165,"remaining_time":3.515908865},
{"learn":[6.115693845],"iteration":55,"passed_time":0.2060415497,"remaining_time":3.473271838},
{"learn":[6.078780782],"iteration":56,"passed_time":0.2070997463,"remaining_time":3.426229137},
{"learn":[6.045146957],"iteration":57,"passed_time":0.2081319679,"remaining_time":3.380350237},
{"learn":[6.008080327],"iteration":58,"passed_time":0.2091958977,"remaining_time":3.336497284},
{"learn":[5.977575734],"iteration":59,"passed_time":0.2103068137,"remaining_time":3.294806748},
{"learn":[5.948036502],"iteration":60,"passed_time":0.2112393159,"remaining_time":3.251700289},
{"learn":[5.914888282],"iteration":61,"passed_time":0.2124934363,"remaining_time":3.214820052},
{"learn":[5.884957796],"iteration":62,"passed_time":0.2142351395,"remaining_time":3.186322631},
{"learn":[5.849539885],"iteration":63,"passed_time":0.2155053158,"remaining_time":3.151765244},
{"learn":[5.821387627],"iteration":64,"passed_time":0.21652531,"remaining_time":3.114633305},
{"learn":[5.797012279],"iteration":65,"passed_time":0.2177099073,"remaining_time":3.080925052},
{"learn":[5.768685095],"iteration":66,"passed_time":0.2188526645,"remaining_time":3.047605014},
{"learn":[5.755484587],"iteration":67,"passed_time":0.2193129441,"remaining_time":3.005877411},
{"learn":[5.731887055],"iteration":68,"passed_time":0.2202635369,"remaining_time":2.971961636},
{"learn":[5.707148487],"iteration":69,"passed_time":0.2212249955,"remaining_time":2.939132084},
{"learn":[5.685365039],"iteration":70,"passed_time":0.2221904626,"remaining_time":2.907252673},
{"learn":[5.663541834],"iteration":71,"passed_time":0.223180901,"remaining_time":2.876553835},
{"learn":[5.638108797],"iteration":72,"passed_time":0.2241394582,"remaining_time":2.846264079},
{"learn":[5.619204893],"iteration":73,"passed_time":0.2250974424,"remaining_time":2.816759887},
{"learn":[5.598472793],"iteration":74,"passed_time":0.226252581,"remaining_time":2.790448499},
{"learn":[5.577007075],"iteration":75,"passed_time":0.2272665587,"remaining_time":2.763082898},
{"learn":[5.562637084],"iteration":76,"passed_time":0.2284705141,"remaining_time":2.73867902},
{"learn":[5.54729991],"iteration":77,"passed_time":0.2298773273,"remaining_time":2.717267894},
{"learn":[5.530737623],"iteration":78,"passed_time":0.2308643186,"remaining_time":2.691468828},
{"learn":[5.513704873],"iteration":79,"passed_time":0.2318326263,"remaining_time":2.666075202},
{"learn":[5.501575529],"iteration":80,"passed_time":0.2329593,"remaining_time":2.643081441},
{"learn":[5.484080734],"iteration":81,"passed_time":0.2339866392,"remaining_time":2.619508961},
{"learn":[5.472178894],"iteration":82,"passed_time":0.2350087413,"remaining_time":2.596421877},
{"learn":[5.458923342],"iteration":83,"passed_time":0.2359946881,"remaining_time":2.573465884},
{"learn":[5.451382371],"iteration":84,"passed_time":0.2366315576,"remaining_time":2.54726912},
{"learn":[5.441410748],"iteration":85,"passed_time":0.2376302845,"remaining_time":2.525512558},
{"learn":[5.434047468],"iteration":86,"passed_time":0.238220736,"remaining_time":2.499948643},
{"learn":[5.422107497],"iteration":87,"passed_time":0.2391878658,"remaining_time":2.478856063},
{"learn":[5.40731265],"iteration":88,"passed_time":0.2402140713,"remaining_time":2.458820437},
{"learn":[5.396360181],"iteration":89,"passed_time":0.2412427791,"remaining_time":2.439232545},
{"learn":[5.383793239],"iteration":90,"passed_time":0.2423945333,"remaining_time":2.421281656},
{"learn":[5.369605034],"iteration":91,"passed_time":0.24361122,"remaining_time":2.404336824},
{"learn":[5.357467333],"iteration":92,"passed_time":0.2451145383,"remaining_time":2.390525659},
{"learn":[5.341109968],"iteration":93,"passed_time":0.2466177591,"remaining_time":2.376975423},
{"learn":[5.330529276],"iteration":94,"passed_time":0.2476064399,"remaining_time":2.358777138},
{"learn":[5.319862075],"iteration":95,"passed_time":0.2485944533,"remaining_time":2.340931102},
{"learn":[5.313052243],"iteration":96,"passed_time":0.24962738,"remaining_time":2.323850764},
{"learn":[5.299677207],"iteration":97,"passed_time":0.2506633426,"remaining_time":2.307125868},
{"learn":[5.287546698],"iteration":98,"passed_time":0.2517906936,"remaining_time":2.291549646},
{"learn":[5.279803754],"iteration":99,"passed_time":0.2529965632,"remaining_time":2.276969069},
{"learn":[5.272254612],"iteration":100,"passed_time":0.2542095414,"remaining_time":2.262716611},
{"learn":[5.268813888],"iteration":101,"passed_time":0.2548075025,"remaining_time":2.243305267},
{"learn":[5.258113767],"iteration":102,"passed_time":0.2557946788,"remaining_time":2.227648805},
{"learn":[5.251018576],"iteration":103,"passed_time":0.2567437605,"remaining_time":2.211946244},
{"learn":[5.24171237],"iteration":104,"passed_time":0.2577387013,"remaining_time":2.196915597},
{"learn":[5.233984943],"iteration":105,"passed_time":0.2594353373,"remaining_time":2.188067844},
{"learn":[5.226240449],"iteration":106,"passed_time":0.2605172402,"remaining_time":2.174223322},
{"learn":[5.220541644],"iteration":107,"passed_time":0.2615389653,"remaining_time":2.160118121},
{"learn":[5.211712096],"iteration":108,"passed_time":0.2627312768,"remaining_time":2.14764741},
{"learn":[5.203388597],"iteration":109,"passed_time":0.2639860082,"remaining_time":2.135886794},
{"learn":[5.196026544],"iteration":110,"passed_time":0.265182556,"remaining_time":2.12384948},
{"learn":[5.188716772],"iteration":111,"passed_time":0.2663883786,"remaining_time":2.112079288},
{"learn":[5.182163132],"iteration":112,"passed_time":0.2675769424,"remaining_time":2.100360601},
{"learn":[5.17764747],"iteration":113,"passed_time":0.2688284087,"remaining_time":2.089315528},
{"learn":[5.170548056],"iteration":114,"passed_time":0.2699877737,"remaining_time":2.077731998},
{"learn":[5.165901827],"iteration":115,"passed_time":0.2707015463,"remaining_time":2.062932474},
{"learn":[5.160333668],"iteration":116,"passed_time":0.2718716759,"remaining_time":2.051817862},
{"learn":[5.148953243],"iteration":117,"passed_time":0.2730170425,"remaining_time":2.040686707},
{"learn":[5.144729126],"iteration":118,"passed_time":0.2742129834,"remaining_time":2.030097802},
{"learn":[5.139939946],"iteration":119,"passed_time":0.2752321325,"remaining_time":2.018368971},
{"learn":[5.132898872],"iteration":120,"passed_time":0.2761783961,"remaining_time":2.006287687},
{"learn":[5.129073077],"iteration":121,"passed_time":0.2772123928,"remaining_time":1.995020335},
{"learn":[5.127123916],"iteration":122,"passed_time":0.2778503052,"remaining_time":1.981095266},
{"learn":[5.121282057],"iteration":123,"passed_time":0.2789460658,"remaining_time":1.970618981},
{"learn":[5.114489821],"iteration":124,"passed_time":0.2800309039,"remaining_time":1.960216327},
{"learn":[5.107777291],"iteration":125,"passed_time":0.2809802879,"remaining_time":1.949021997},
{"learn":[5.103518754],"iteration":126,"passed_time":0.2819778053,"remaining_time":1.938319874},
{"learn":[5.101133351],"iteration":127,"passed_time":0.2826506252,"remaining_time":1.925557384},
{"learn":[5.096462705],"iteration":128,"passed_time":0.2838429405,"remaining_time":1.916489931},
{"learn":[5.08562082],"iteration":129,"passed_time":0.284994997,"remaining_time":1.90727421},
{"learn":[5.080483682],"iteration":130,"passed_time":0.2862228082,"remaining_time":1.898684125},
{"learn":[5.07437499],"iteration":131,"passed_time":0.2873508902,"remaining_time":1.889549793},
{"learn":[5.070683732],"iteration":132,"passed_time":0.2883206723,"remaining_time":1.879503931},
{"learn":[5.06432037],"iteration":133,"passed_time":0.2900543211,"remaining_time":1.874530165},
{"learn":[5.057436484],"iteration":134,"passed_time":0.2917085729,"remaining_time":1.869095671},
{"learn":[5.053254656],"iteration":135,"passed_time":0.2927232703,"remaining_time":1.859653717},
{"learn":[5.04801663],"iteration":136,"passed_time":0.2937374763,"remaining_time":1.850331693},
{"learn":[5.045680836],"iteration":137,"passed_time":0.2944820604,"remaining_time":1.839445913},
{"learn":[5.041857933],"iteration":138,"passed_time":0.2955447819,"remaining_time":1.830676671},
{"learn":[5.035264888],"iteration":139,"passed_time":0.2965218121,"remaining_time":1.821491131},
{"learn":[5.028771948],"iteration":140,"passed_time":0.2977448289,"remaining_time":1.813920625},
{"learn":[5.024912247],"iteration":141,"passed_time":0.2987218125,"remaining_time":1.804952923},
{"learn":[5.02239068],"iteration":142,"passed_time":0.2998085581,"remaining_time":1.796754785},
{"learn":[5.017110572],"iteration":143,"passed_time":0.3008381124,"remaining_time":1.788315446},
{"learn":[5.010707886],"iteration":144,"passed_time":0.3018176574,"remaining_time":1.779683428},
{"learn":[5.004389868],"iteration":145,"passed_time":0.3027597476,"remaining_time":1.770937154},
{"learn":[4.997628683],"iteration":146,"passed_time":0.3042377547,"remaining_time":1.765406835},
{"learn":[4.991497851],"iteration":147,"passed_time":0.3053992347,"remaining_time":1.758109108},
{"learn":[4.988345253],"iteration":148,"passed_time":0.306446458,"remaining_time":1.75024118},
{"learn":[4.98460423],"iteration":149,"passed_time":0.3076038754,"remaining_time":1.743088627},
{"learn":[4.982441783],"iteration":150,"passed_time":0.3087742924,"remaining_time":1.736088571},
{"learn":[4.977461771],"iteration":151,"passed_time":0.3100033361,"remaining_time":1.729492296},
{"learn":[4.973601586],"iteration":152,"passed_time":0.311201694,"remaining_time":1.722796306},
{"learn":[4.968328804],"iteration":153,"passed_time":0.3122237994,"remaining_time":1.71520347},
{"learn":[4.9640736],"iteration":154,"passed_time":0.3132948911,"remaining_time":1.707962471},
{"learn":[4.960865882],"iteration":155,"passed_time":0.3143170798,"remaining_time":1.700535996},
{"learn":[4.957014156],"iteration":156,"passed_time":0.3154713288,"remaining_time":1.693900192},
{"learn":[4.952244852],"iteration":157,"passed_time":0.316533887,"remaining_time":1.686845145},
{"learn":[4.949695675],"iteration":158,"passed_time":0.3174456722,"remaining_time":1.679067989},
{"learn":[4.946584698],"iteration":159,"passed_time":0.3184052907,"remaining_time":1.671627776},
{"learn":[4.940192834],"iteration":160,"passed_time":0.3200576932,"remaining_time":1.667878289},
{"learn":[4.936727994],"iteration":161,"passed_time":0.3213074639,"remaining_time":1.662071943},
{"learn":[4.932342063],"iteration":162,"passed_time":0.3225354793,"remaining_time":1.656209792},
{"learn":[4.925830838],"iteration":163,"passed_time":0.3236492425,"remaining_time":1.649821748},
{"learn":[4.922571773],"iteration":164,"passed_time":0.3246361306,"remaining_time":1.64285557},
{"learn":[4.918395814],"iteration":165,"passed_time":0.3256947341,"remaining_time":1.636321736},
{"learn":[4.911142452],"iteration":166,"passed_time":0.3269085932,"remaining_time":1.630627893},
{"learn":[4.908276131],"iteration":167,"passed_time":0.328121576,"remaining_time":1.624983043},
{"learn":[4.904584645],"iteration":168,"passed_time":0.3293192775,"remaining_time":1.619315501},
{"learn":[4.89795517],"iteration":169,"passed_time":0.3305933231,"remaining_time":1.614073283},
{"learn":[4.895556491],"iteration":170,"passed_time":0.331795777,"remaining_time":1.608530404},
{"learn":[4.890591233],"iteration":171,"passed_time":0.3328525745,"remaining_time":1.602336812},
{"learn":[4.884629277],"iteration":172,"passed_time":0.3345842184,"remaining_time":1.599428605},
{"learn":[4.880550786],"iteration":173,"passed_time":0.3359820845,"remaining_time":1.594949436},
{"learn":[4.876384842],"iteration":174,"passed_time":0.3373754803,"remaining_time":1.590484407},
{"learn":[4.872638238],"iteration":175,"passed_time":0.3384414414,"remaining_time":1.584521294},
{"learn":[4.869137118],"iteration":176,"passed_time":0.3394123064,"remaining_time":1.578171346},
{"learn":[4.863587157],"iteration":177,"passed_time":0.3409631665,"remaining_time":1.574560241},
{"learn":[4.858028614],"iteration":178,"passed_time":0.342289241,"remaining_time":1.569941156},
{"learn":[4.853838176],"iteration":179,"passed_time":0.3434037973,"remaining_time":1.564395077},
{"learn":[4.853462329],"iteration":180,"passed_time":0.343949064,"remaining_time":1.556322008},
{"learn":[4.851573196],"iteration":181,"passed_time":0.3451577059,"remaining_time":1.551313206},
{"learn":[4.848442087],"iteration":182,"passed_time":0.3461190221,"remaining_time":1.545241754},
{"learn":[4.845547104],"iteration":183,"passed_time":0.3470653607,"remaining_time":1.539159426},
{"learn":[4.839868817],"iteration":184,"passed_time":0.3480612378,"remaining_time":1.533350858},
{"learn":[4.836336958],"iteration":185,"passed_time":0.3495005793,"remaining_time":1.529534793},
{"learn":[4.831124789],"iteration":186,"passed_time":0.3509240548,"remaining_time":1.525675169},
{"learn":[4.827407333],"iteration":187,"passed_time":0.3520921077,"remaining_time":1.520738252},
{"learn":[4.824088918],"iteration":188,"passed_time":0.3531452258,"remaining_time":1.515348033},
{"learn":[4.820934539],"iteration":189,"passed_time":0.3541037748,"remaining_time":1.509600303},
{"learn":[4.816975227],"iteration":190,"passed_time":0.3554055764,"remaining_time":1.505356604},
{"learn":[4.812340486],"iteration":191,"passed_time":0.3564857946,"remaining_time":1.500211052},
{"learn":[4.806402747],"iteration":192,"passed_time":0.3576403139,"remaining_time":1.495418307},
{"learn":[4.801521788],"iteration":193,"passed_time":0.3586785494,"remaining_time":1.490179953},
{"learn":[4.797601172],"iteration":194,"passed_time":0.3597186521,"remaining_time":1.484992384},
{"learn":[4.792694629],"iteration":195,"passed_time":0.3609098665,"remaining_time":1.480467003},
{"learn":[4.789794613],"iteration":196,"passed_time":0.3620385107,"remaining_time":1.475720427},
{"learn":[4.785367055],"iteration":197,"passed_time":0.3630987078,"remaining_time":1.47073315},
{"learn":[4.780376856],"iteration":198,"passed_time":0.3648283757,"remaining_time":1.468480045},
{"learn":[4.776691261],"iteration":199,"passed_time":0.3660175468,"remaining_time":1.464070187},
{"learn":[4.773470753],"iteration":200,"passed_time":0.3672311605,"remaining_time":1.459789539},
{"learn":[4.77207327],"iteration":201,"passed_time":0.3704542926,"remaining_time":1.463477849},
{"learn":[4.767347177],"iteration":202,"passed_time":0.3841904116,"remaining_time":1.508373192},
{"learn":[4.763983068],"iteration":203,"passed_time":0.3851991996,"remaining_time":1.503032171},
{"learn":[4.761588849],"iteration":204,"passed_time":0.3861890673,"remaining_time":1.497660042},
{"learn":[4.758558086],"iteration":205,"passed_time":0.3872173404,"remaining_time":1.492478487},
{"learn":[4.753678804],"iteration":206,"passed_time":0.3883125095,"remaining_time":1.487593333},
{"learn":[4.746510889],"iteration":207,"passed_time":0.389390359,"remaining_time":1.482678675},
{"learn":[4.744840601],"iteration":208,"passed_time":0.3905111958,"remaining_time":1.477963425},
{"learn":[4.741702222],"iteration":209,"passed_time":0.391696976,"remaining_time":1.473526719},
{"learn":[4.739352853],"iteration":210,"passed_time":0.3927146769,"remaining_time":1.468492323},
{"learn":[4.735539287],"iteration":211,"passed_time":0.3936876194,"remaining_time":1.463329453},
{"learn":[4.730726751],"iteration":212,"passed_time":0.3946318772,"remaining_time":1.45809994},
{"learn":[4.726416092],"iteration":213,"passed_time":0.3964374327,"remaining_time":1.456073935},
{"learn":[4.721293082],"iteration":214,"passed_time":0.3978817365,"remaining_time":1.452730991},
{"learn":[4.718443695],"iteration":215,"passed_time":0.3990398332,"remaining_time":1.448366802},
{"learn":[4.711627962],"iteration":216,"passed_time":0.4002240311,"remaining_time":1.444126343},
{"learn":[4.709790764],"iteration":217,"passed_time":0.4012362116,"remaining_time":1.439296869},
{"learn":[4.706913073],"iteration":218,"passed_time":0.4022512172,"remaining_time":1.434512332},
{"learn":[4.703846389],"iteration":219,"passed_time":0.4032383002,"remaining_time":1.429663064},
{"learn":[4.701001135],"iteration":220,"passed_time":0.4042137443,"remaining_time":1.424807723},
{"learn":[4.700380864],"iteration":221,"passed_time":0.4053394051,"remaining_time":1.420513771},
{"learn":[4.695837486],"iteration":222,"passed_time":0.4063318239,"remaining_time":1.415783978},
{"learn":[4.691242996],"iteration":223,"passed_time":0.4072538135,"remaining_time":1.410843568},
{"learn":[4.690284609],"iteration":224,"passed_time":0.4083617661,"remaining_time":1.406579416},
{"learn":[4.68827119],"iteration":225,"passed_time":0.4097969529,"remaining_time":1.403463901},
{"learn":[4.686922425],"iteration":226,"passed_time":0.411518274,"remaining_time":1.401337559},
{"learn":[4.686085874],"iteration":227,"passed_time":0.412486665,"remaining_time":1.396665374},
{"learn":[4.683230741],"iteration":228,"passed_time":0.4134648201,"remaining_time":1.392058412},
{"learn":[4.6773487],"iteration":229,"passed_time":0.4146396054,"remaining_time":1.388141288},
{"learn":[4.671462906],"iteration":230,"passed_time":0.4158746827,"remaining_time":1.384448619},
{"learn":[4.664799601],"iteration":231,"passed_time":0.4170750865,"remaining_time":1.380662355},
{"learn":[4.660979386],"iteration":232,"passed_time":0.4182109309,"remaining_time":1.376685768},
{"learn":[4.656281279],"iteration":233,"passed_time":0.4192486253,"remaining_time":1.372412167},
{"learn":[4.651997094],"iteration":234,"passed_time":0.4202189664,"remaining_time":1.367946848},
{"learn":[4.650151977],"iteration":235,"passed_time":0.4211983615,"remaining_time":1.363540458},
{"learn":[4.648478046],"iteration":236,"passed_time":0.4221741938,"remaining_time":1.359151518},
{"learn":[4.646364602],"iteration":237,"passed_time":0.4235729925,"remaining_time":1.356145463},
{"learn":[4.642635873],"iteration":238,"passed_time":0.424684173,"remaining_time":1.352237053},
{"learn":[4.640860821],"iteration":239,"passed_time":0.42633771,"remaining_time":1.350069415},
{"learn":[4.639446822],"iteration":240,"passed_time":0.4275996886,"remaining_time":1.346672878},
{"learn":[4.637120072],"iteration":241,"passed_time":0.4286752635,"remaining_time":1.342710123},
{"learn":[4.633769267],"iteration":242,"passed_time":0.4297511634,"remaining_time":1.338772143},
{"learn":[4.630491517],"iteration":243,"passed_time":0.4310025139,"remaining_time":1.335401232},
{"learn":[4.627813333],"iteration":244,"passed_time":0.432196788,"remaining_time":1.331871735},
{"learn":[4.622496304],"iteration":245,"passed_time":0.4334085771,"remaining_time":1.328414907},
{"learn":[4.618979301],"iteration":246,"passed_time":0.4345328505,"remaining_time":1.324709459},
{"learn":[4.616563458],"iteration":247,"passed_time":0.4356844771,"remaining_time":1.321107769},
{"learn":[4.614759385],"iteration":248,"passed_time":0.4367580362,"remaining_time":1.317290302},
{"learn":[4.61251363],"iteration":249,"passed_time":0.4380315762,"remaining_time":1.314094729},
{"learn":[4.608796693],"iteration":250,"passed_time":0.4392479589,"remaining_time":1.310743909},
{"learn":[4.60847774],"iteration":251,"passed_time":0.4408493634,"remaining_time":1.308552872},
{"learn":[4.605195659],"iteration":252,"passed_time":0.4418494006,"remaining_time":1.304590918},
{"learn":[4.60103766],"iteration":253,"passed_time":0.4430179333,"remaining_time":1.301147158},
{"learn":[4.599325598],"iteration":254,"passed_time":0.4440239124,"remaining_time":1.297246332},
{"learn":[4.597012808],"iteration":255,"passed_time":0.444971742,"remaining_time":1.293199125},
{"learn":[4.594161533],"iteration":256,"passed_time":0.4460053997,"remaining_time":1.289424171},
{"learn":[4.592197259],"iteration":257,"passed_time":0.4469439521,"remaining_time":1.285396947},
{"learn":[4.58952828],"iteration":258,"passed_time":0.4479060971,"remaining_time":1.281461073},
{"learn":[4.585816572],"iteration":259,"passed_time":0.4488435216,"remaining_time":1.277477715},
{"learn":[4.582934052],"iteration":260,"passed_time":0.4499136324,"remaining_time":1.273893388},
{"learn":[4.582234842],"iteration":261,"passed_time":0.4508593279,"remaining_time":1.269977801},
{"learn":[4.57571562],"iteration":262,"passed_time":0.4519691889,"remaining_time":1.266544837},
{"learn":[4.571197349],"iteration":263,"passed_time":0.4532061296,"remaining_time":1.263483755},
{"learn":[4.56723703],"iteration":264,"passed_time":0.4543659997,"remaining_time":1.260222679},
{"learn":[4.560335567],"iteration":265,"passed_time":0.4558901101,"remaining_time":1.257982484},
{"learn":[4.554709345],"iteration":266,"passed_time":0.4568629002,"remaining_time":1.254234104},
{"learn":[4.552806306],"iteration":267,"passed_time":0.4578023364,"remaining_time":1.250415337},
{"learn":[4.550766241],"iteration":268,"passed_time":0.4587944945,"remaining_time":1.246761247},
{"learn":[4.549216045],"iteration":269,"passed_time":0.459957057,"remaining_time":1.243587599},
{"learn":[4.547687452],"iteration":270,"passed_time":0.4611177348,"remaining_time":1.240423722},
{"learn":[4.545642435],"iteration":271,"passed_time":0.462268663,"remaining_time":1.23724848},
{"learn":[4.543930359],"iteration":272,"passed_time":0.4633941909,"remaining_time":1.234020428},
{"learn":[4.541029943],"iteration":273,"passed_time":0.4643746947,"remaining_time":1.230423461},
{"learn":[4.537781449],"iteration":274,"passed_time":0.4653318917,"remaining_time":1.226784078},
{"learn":[4.53066128],"iteration":275,"passed_time":0.4663822188,"remaining_time":1.223408429},
{"learn":[4.526763956],"iteration":276,"passed_time":0.4674534262,"remaining_time":1.220104069},
{"learn":[4.522036004],"iteration":277,"passed_time":0.4684689392,"remaining_time":1.21667113},
{"learn":[4.515307629],"iteration":278,"passed_time":0.4696283458,"remaining_time":1.213627374},
{"learn":[4.51109143],"iteration":279,"passed_time":0.4714100746,"remaining_time":1.212197335},
{"learn":[4.508233494],"iteration":280,"passed_time":0.4730235865,"remaining_time":1.210334373},
{"learn":[4.502555629],"iteration":281,"passed_time":0.4740782603,"remaining_time":1.207050322},
{"learn":[4.500081355],"iteration":282,"passed_time":0.4751198557,"remaining_time":1.203748892},
{"learn":[4.495281743],"iteration":283,"passed_time":0.4761316251,"remaining_time":1.200388182},
{"learn":[4.492138869],"iteration":284,"passed_time":0.4771891178,"remaining_time":1.197158664},
{"learn":[4.491708261],"iteration":285,"passed_time":0.4782693272,"remaining_time":1.194001048},
{"learn":[4.489398865],"iteration":286,"passed_time":0.4792419745,"remaining_time":1.190590689},
{"learn":[4.485796373],"iteration":287,"passed_time":0.4808834087,"remaining_time":1.188850649},
{"learn":[4.479542205],"iteration":288,"passed_time":0.4820158781,"remaining_time":1.185859133},
{"learn":[4.475986993],"iteration":289,"passed_time":0.4829839184,"remaining_time":1.182477869},
{"learn":[4.468661855],"iteration":290,"passed_time":0.4839816206,"remaining_time":1.179185461},
{"learn":[4.463785664],"iteration":291,"passed_time":0.4849562159,"remaining_time":1.175852743},
{"learn":[4.460445831],"iteration":292,"passed_time":0.4864411895,"remaining_time":1.173767648},
{"learn":[4.45692492],"iteration":293,"passed_time":0.4875697717,"remaining_time":1.170830812},
{"learn":[4.454031688],"iteration":294,"passed_time":0.4888183546,"remaining_time":1.168193017},
{"learn":[4.451672391],"iteration":295,"passed_time":0.4900053914,"remaining_time":1.165418228},
{"learn":[4.45031553],"iteration":296,"passed_time":0.4911995456,"remaining_time":1.162670978},
{"learn":[4.446782666],"iteration":297,"passed_time":0.4922184955,"remaining_time":1.159521422},
{"learn":[4.444369689],"iteration":298,"passed_time":0.4934417702,"remaining_time":1.156865153},
{"learn":[4.44411683],"iteration":299,"passed_time":0.4950638838,"remaining_time":1.155149062},
{"learn":[4.440876943],"iteration":300,"passed_time":0.4965083913,"remaining_time":1.153021148},
{"learn":[4.439336453],"iteration":301,"passed_time":0.497691513,"remaining_time":1.150293629},
{"learn":[4.436666901],"iteration":302,"passed_time":0.4987405731,"remaining_time":1.147267919},
{"learn":[4.433043336],"iteration":303,"passed_time":0.4998810369,"remaining_time":1.144464479},
{"learn":[4.431419305],"iteration":304,"passed_time":0.501459439,"remaining_time":1.142669869},
{"learn":[4.428859646],"iteration":305,"passed_time":0.5025401024,"remaining_time":1.139747814},
{"learn":[4.424552441],"iteration":306,"passed_time":0.5037393313,"remaining_time":1.137105396},
{"learn":[4.422706391],"iteration":307,"passed_time":0.5049604447,"remaining_time":1.134521519},
{"learn":[4.421427994],"iteration":308,"passed_time":0.5061175776,"remaining_time":1.131803385},
{"learn":[4.418733158],"iteration":309,"passed_time":0.5073612211,"remaining_time":1.129287879},
{"learn":[4.415656941],"iteration":310,"passed_time":0.5085966382,"remaining_time":1.126762327},
{"learn":[4.410747417],"iteration":311,"passed_time":0.5096347991,"remaining_time":1.12381007},
{"learn":[4.408126521],"iteration":312,"passed_time":0.5106049752,"remaining_time":1.120720824},
{"learn":[4.407843853],"iteration":313,"passed_time":0.5115418466,"remaining_time":1.117572315},
{"learn":[4.405219398],"iteration":314,"passed_time":0.5125460455,"remaining_time":1.114584258},
{"learn":[4.402708465],"iteration":315,"passed_time":0.5135390371,"remaining_time":1.111584498},
{"learn":[4.40104971],"iteration":316,"passed_time":0.5145152317,"remaining_time":1.108561209},
{"learn":[4.400830038],"iteration":317,"passed_time":0.5158172542,"remaining_time":1.106249583},
{"learn":[4.39784288],"iteration":318,"passed_time":0.5177054801,"remaining_time":1.105195711},
{"learn":[4.393741845],"iteration":319,"passed_time":0.5192300636,"remaining_time":1.103363885},
{"learn":[4.393425936],"iteration":320,"passed_time":0.5204435004,"remaining_time":1.100875815},
{"learn":[4.390505974],"iteration":321,"passed_time":0.5216871322,"remaining_time":1.098459241},
{"learn":[4.390305136],"iteration":322,"passed_time":0.5228531759,"remaining_time":1.095887307},
{"learn":[4.38568203],"iteration":323,"passed_time":0.5238589996,"remaining_time":1.092989765},
{"learn":[4.383057135],"iteration":324,"passed_time":0.5250031296,"remaining_time":1.090391115},
{"learn":[4.380662684],"iteration":325,"passed_time":0.5260409169,"remaining_time":1.087581528},
{"learn":[4.37805727],"iteration":326,"passed_time":0.5272650458,"remaining_time":1.085166287},
{"learn":[4.373708319],"iteration":327,"passed_time":0.5284560332,"remaining_time":1.08269041},
{"learn":[4.36887921],"iteration":328,"passed_time":0.5299299898,"remaining_time":1.080799463},
{"learn":[4.367895929],"iteration":329,"passed_time":0.5317107011,"remaining_time":1.079533848},
{"learn":[4.362140573],"iteration":330,"passed_time":0.5327344442,"remaining_time":1.076735176},
{"learn":[4.361931924],"iteration":331,"passed_time":0.5338481417,"remaining_time":1.074128189},
{"learn":[4.359656377],"iteration":332,"passed_time":0.5350074508,"remaining_time":1.071621531},
{"learn":[4.354281355],"iteration":333,"passed_time":0.5361356681,"remaining_time":1.069060943},
{"learn":[4.348589447],"iteration":334,"passed_time":0.5371381677,"remaining_time":1.066259348},
{"learn":[4.346355698],"iteration":335,"passed_time":0.5381075958,"remaining_time":1.063403106},
{"learn":[4.343894047],"iteration":336,"passed_time":0.5390914133,"remaining_time":1.060586371},
{"learn":[4.341561356],"iteration":337,"passed_time":0.5401777958,"remaining_time":1.057981363},
{"learn":[4.338869061],"iteration":338,"passed_time":0.5413070115,"remaining_time":1.055468834},
{"learn":[4.333720063],"iteration":339,"passed_time":0.5423044409,"remaining_time":1.052708621},
{"learn":[4.330892223],"iteration":340,"passed_time":0.5436443693,"remaining_time":1.050620643},
{"learn":[4.328311474],"iteration":341,"passed_time":0.5447695202,"remaining_time":1.048123814},
{"learn":[4.324580133],"iteration":342,"passed_time":0.5465628875,"remaining_time":1.046914919},
{"learn":[4.323354432],"iteration":343,"passed_time":0.54776879,"remaining_time":1.044582344},
{"learn":[4.323159553],"iteration":344,"passed_time":0.5489382857,"remaining_time":1.04218718},
{"learn":[4.318639682],"iteration":345,"passed_time":0.550120444,"remaining_time":1.039823036},
{"learn":[4.312712208],"iteration":346,"passed_time":0.5512445225,"remaining_time":1.037356407},
{"learn":[4.311461062],"iteration":347,"passed_time":0.5524258503,"remaining_time":1.035004754},
{"learn":[4.311178356],"iteration":348,"passed_time":0.5534529205,"remaining_time":1.032372067},
{"learn":[4.311102505],"iteration":349,"passed_time":0.5546363179,"remaining_time":1.030038876},
{"learn":[4.310232308],"iteration":350,"passed_time":0.555581157,"remaining_time":1.027271142},
{"learn":[4.305128197],"iteration":351,"passed_time":0.5565502911,"remaining_time":1.02455849},
{"learn":[4.304595496],"iteration":352,"passed_time":0.5574912475,"remaining_time":1.021804071},
{"learn":[4.3004992],"iteration":353,"passed_time":0.5585586656,"remaining_time":1.019290672},
{"learn":[4.297581524],"iteration":354,"passed_time":0.5595134601,"remaining_time":1.016580794},
{"learn":[4.297355825],"iteration":355,"passed_time":0.5608018044,"remaining_time":1.014484163},
{"learn":[4.295758715],"iteration":356,"passed_time":0.5622562973,"remaining_time":1.012691314},
{"learn":[4.292500657],"iteration":357,"passed_time":0.5635050492,"remaining_time":1.010531401},
{"learn":[4.290797586],"iteration":358,"passed_time":0.5645498168,"remaining_time":1.008012347},
{"learn":[4.286410608],"iteration":359,"passed_time":0.5655617753,"remaining_time":1.005443156},
{"learn":[4.280278245],"iteration":360,"passed_time":0.5665734863,"remaining_time":1.002882154},
{"learn":[4.279941283],"iteration":361,"passed_time":0.5675172534,"remaining_time":1.000209966},
{"learn":[4.274426275],"iteration":362,"passed_time":0.5686338601,"remaining_time":0.9978506031},
{"learn":[4.273567658],"iteration":363,"passed_time":0.5696980786,"remaining_time":0.9954065329},
{"learn":[4.269488271],"iteration":364,"passed_time":0.5706671893,"remaining_time":0.9928045622},
{"learn":[4.266838205],"iteration":365,"passed_time":0.571671205,"remaining_time":0.990271978},
{"learn":[4.263456509],"iteration":366,"passed_time":0.572950257,"remaining_time":0.9882221054},
{"learn":[4.260360204],"iteration":367,"passed_time":0.5739686938,"remaining_time":0.9857288438},
{"learn":[4.255120549],"iteration":368,"passed_time":0.5751289897,"remaining_time":0.9834861585},
{"learn":[4.252582211],"iteration":369,"passed_time":0.5766888913,"remaining_time":0.9819297339},
{"learn":[4.247857931],"iteration":370,"passed_time":0.5778021131,"remaining_time":0.9796159815},
{"learn":[4.245288911],"iteration":371,"passed_time":0.5790519634,"remaining_time":0.9775393361},
{"learn":[4.24048515],"iteration":372,"passed_time":0.5802551699,"remaining_time":0.9753887173},
{"learn":[4.2378365],"iteration":373,"passed_time":0.5815004245,"remaining_time":0.9733135448},
{"learn":[4.236751063],"iteration":374,"passed_time":0.5826933587,"remaining_time":0.9711555978},
{"learn":[4.233240093],"iteration":375,"passed_time":0.5839022668,"remaining_time":0.9690292938},
{"learn":[4.230358421],"iteration":376,"passed_time":0.5851174778,"remaining_time":0.9669182724},
{"learn":[4.225853583],"iteration":377,"passed_time":0.5863376174,"remaining_time":0.9648201007},
{"learn":[4.224702126],"iteration":378,"passed_time":0.5882578445,"remaining_time":0.9638736713},
{"learn":[4.224361982],"iteration":379,"passed_time":0.5893139973,"remaining_time":0.9615123114},
{"learn":[4.223787954],"iteration":380,"passed_time":0.5904454817,"remaining_time":0.959280192},
{"learn":[4.22144054],"iteration":381,"passed_time":0.5919261261,"remaining_time":0.9576187067},
{"learn":[4.217739335],"iteration":382,"passed_time":0.5929056828,"remaining_time":0.9551509303},
{"learn":[4.215611665],"iteration":383,"passed_time":0.5939901081,"remaining_time":0.9528591318},
{"learn":[4.210236863],"iteration":384,"passed_time":0.5950582722,"remaining_time":0.9505476296},
{"learn":[4.208454294],"iteration":385,"passed_time":0.5960633641,"remaining_time":0.9481422424},
{"learn":[4.207446501],"iteration":386,"passed_time":0.5971712742,"remaining_time":0.9459069536},
{"learn":[4.204985442],"iteration":387,"passed_time":0.5984127035,"remaining_time":0.9438880788},
{"learn":[4.202796622],"iteration":388,"passed_time":0.5995799755,"remaining_time":0.9417567224},
{"learn":[4.199774004],"iteration":389,"passed_time":0.6005468728,"remaining_time":0.9393169037},
{"learn":[4.199458358],"iteration":390,"passed_time":0.6015868943,"remaining_time":0.9369985131},
{"learn":[4.19751254],"iteration":391,"passed_time":0.6026290412,"remaining_time":0.9346899415},
{"learn":[4.195201346],"iteration":392,"passed_time":0.6037559236,"remaining_time":0.9325186912},
{"learn":[4.190593508],"iteration":393,"passed_time":0.6047095602,"remaining_time":0.9300862779},
{"learn":[4.187212054],"iteration":394,"passed_time":0.6060111587,"remaining_time":0.9281943063},
{"learn":[4.184984466],"iteration":395,"passed_time":0.6074555437,"remaining_time":0.926523102},
{"learn":[4.182832144],"iteration":396,"passed_time":0.6089288539,"remaining_time":0.9248969745},
{"learn":[4.179752812],"iteration":397,"passed_time":0.6099402467,"remaining_time":0.922572936},
{"learn":[4.17878934],"iteration":398,"passed_time":0.6109080912,"remaining_time":0.9201898818},
{"learn":[4.174548229],"iteration":399,"passed_time":0.6119477199,"remaining_time":0.9179215799},
{"learn":[4.168872556],"iteration":400,"passed_time":0.6130348625,"remaining_time":0.9157303807},
{"learn":[4.163926494],"iteration":401,"passed_time":0.6142649283,"remaining_time":0.9137572815},
{"learn":[4.159485076],"iteration":402,"passed_time":0.6156421357,"remaining_time":0.9120058438},
{"learn":[4.155926102],"iteration":403,"passed_time":0.6168663076,"remaining_time":0.9100304933},
{"learn":[4.153540115],"iteration":404,"passed_time":0.6179301907,"remaining_time":0.9078233666},
{"learn":[4.150983044],"iteration":405,"passed_time":0.6189163016,"remaining_time":0.9055080866},
{"learn":[4.146539132],"iteration":406,"passed_time":0.6198865094,"remaining_time":0.9031761672},
{"learn":[4.144869174],"iteration":407,"passed_time":0.6208328921,"remaining_time":0.9008163532},
{"learn":[4.142825962],"iteration":408,"passed_time":0.6221081439,"remaining_time":0.8989386628},
{"learn":[4.142467378],"iteration":409,"passed_time":0.6233238973,"remaining_time":0.8969782912},
{"learn":[4.141800768],"iteration":410,"passed_time":0.6245215539,"remaining_time":0.8949956088},
{"learn":[4.140107084],"iteration":411,"passed_time":0.6257057039,"remaining_time":0.8929974609},
{"learn":[4.136243196],"iteration":412,"passed_time":0.6269958784,"remaining_time":0.8911539482},
{"learn":[4.133618439],"iteration":413,"passed_time":0.6282055328,"remaining_time":0.8891991358},
{"learn":[4.131053025],"iteration":414,"passed_time":0.6295998195,"remaining_time":0.8875081793},
{"learn":[4.128379975],"iteration":415,"passed_time":0.6307621171,"remaining_time":0.8854929721},
{"learn":[4.127068571],"iteration":416,"passed_time":0.6319468307,"remaining_time":0.8835131949},
{"learn":[4.125969877],"iteration":417,"passed_time":0.6330899364,"remaining_time":0.8814792895},
{"learn":[4.123893633],"iteration":418,"passed_time":0.6342279487,"remaining_time":0.8794425733},
{"learn":[4.119643722],"iteration":419,"passed_time":0.6353906033,"remaining_time":0.8774441664},
{"learn":[4.11465686],"iteration":420,"passed_time":0.63707429,"remaining_time":0.8761663038},
{"learn":[4.111565986],"iteration":421,"passed_time":0.6383155136,"remaining_time":0.8742804902},
{"learn":[4.106322452],"iteration":422,"passed_time":0.6395549346,"remaining_time":0.8723952654},
{"learn":[4.104222175],"iteration":423,"passed_time":0.6407975985,"remaining_time":0.8705174923},
{"learn":[4.103008002],"iteration":424,"passed_time":0.641950069,"remaining_time":0.8685206816},
{"learn":[4.099176337],"iteration":425,"passed_time":0.643119164,"remaining_time":0.8665502351},
{"learn":[4.096525716],"iteration":426,"passed_time":0.6443629512,"remaining_time":0.864683773},
{"learn":[4.094967724],"iteration":427,"passed_time":0.6456171736,"remaining_time":0.8628341666},
{"learn":[4.094683584],"iteration":428,"passed_time":0.6467004868,"remaining_time":0.8607598555},
{"learn":[4.091096563],"iteration":429,"passed_time":0.6477570882,"remaining_time":0.8586547449},
{"learn":[4.089178677],"iteration":430,"passed_time":0.6487151865,"remaining_time":0.8564244573},
{"learn":[4.085335077],"iteration":431,"passed_time":0.6497095733,"remaining_time":0.8542477723},
{"learn":[4.084852122],"iteration":432,"passed_time":0.6513853085,"remaining_time":0.8529687527},
{"learn":[4.080322952],"iteration":433,"passed_time":0.6527745255,"remaining_time":0.8513142429},
{"learn":[4.077449519],"iteration":434,"passed_time":0.6541489223,"remaining_time":0.8496417037},
{"learn":[4.076568374],"iteration":435,"passed_time":0.6554619784,"remaining_time":0.8478911831},
{"learn":[4.076071793],"iteration":436,"passed_time":0.6565331259,"remaining_time":0.8458310066},
{"learn":[4.075027644],"iteration":437,"passed_time":0.6575041201,"remaining_time":0.843646839},
{"learn":[4.07020837],"iteration":438,"passed_time":0.6584468034,"remaining_time":0.8414320198},
{"learn":[4.06833694],"iteration":439,"passed_time":0.6594314373,"remaining_time":0.8392763747},
{"learn":[4.063936568],"iteration":440,"passed_time":0.6603686594,"remaining_time":0.8370659424},
{"learn":[4.061734926],"iteration":441,"passed_time":0.661267901,"remaining_time":0.8348133229},
{"learn":[4.060815619],"iteration":442,"passed_time":0.6623890993,"remaining_time":0.8328458878},
{"learn":[4.056407489],"iteration":443,"passed_time":0.6634048588,"remaining_time":0.8307502286},
{"learn":[4.05238936],"iteration":444,"passed_time":0.6643848062,"remaining_time":0.8286147583},
{"learn":[4.049685254],"iteration":445,"passed_time":0.6653435625,"remaining_time":0.8264581471},
{"learn":[4.045162016],"iteration":446,"passed_time":0.6670482108,"remaining_time":0.8252296657},
{"learn":[4.042955482],"iteration":447,"passed_time":0.6681991652,"remaining_time":0.8233168286},
{"learn":[4.041467663],"iteration":448,"passed_time":0.6692933081,"remaining_time":0.8213376676},
{"learn":[4.038920476],"iteration":449,"passed_time":0.6703465466,"remaining_time":0.8193124458},
{"learn":[4.036694383],"iteration":450,"passed_time":0.6715987856,"remaining_time":0.8175337767},
{"learn":[4.034999007],"iteration":451,"passed_time":0.6727681621,"remaining_time":0.8156569753},
{"learn":[4.031928018],"iteration":452,"passed_time":0.6739558491,"remaining_time":0.8138054072},
{"learn":[4.028718143],"iteration":453,"passed_time":0.6751255339,"remaining_time":0.8119351134},
{"learn":[4.027401978],"iteration":454,"passed_time":0.6763077797,"remaining_time":0.8100829449},
{"learn":[4.025930598],"iteration":455,"passed_time":0.677326134,"remaining_time":0.808038195},
{"learn":[4.021074523],"iteration":456,"passed_time":0.6785399377,"remaining_time":0.8062301667},
{"learn":[4.020268486],"iteration":457,"passed_time":0.6795489206,"remaining_time":0.8041823471},
{"learn":[4.017986361],"iteration":458,"passed_time":0.6808050448,"remaining_time":0.8024303469},
{"learn":[4.014814804],"iteration":459,"passed_time":0.6818426276,"remaining_time":0.8004239542},
{"learn":[4.009704796],"iteration":460,"passed_time":0.6828263552,"remaining_time":0.7983587971},
{"learn":[4.008440457],"iteration":461,"passed_time":0.6837814821,"remaining_time":0.796265016},
{"learn":[4.004854849],"iteration":462,"passed_time":0.6848546801,"remaining_time":0.7943130954},
{"learn":[4.000898028],"iteration":463,"passed_time":0.685903611,"remaining_time":0.79233693},
{"learn":[3.996617985],"iteration":464,"passed_time":0.6869092627,"remaining_time":0.7903149582},
{"learn":[3.995443319],"iteration":465,"passed_time":0.6880426689,"remaining_time":0.788443745},
{"learn":[3.990771995],"iteration":466,"passed_time":0.6893259018,"remaining_time":0.7867466931},
{"learn":[3.989249359],"iteration":467,"passed_time":0.6905153015,"remaining_time":0.7849447445},
{"learn":[3.986599538],"iteration":468,"passed_time":0.6916921194,"remaining_time":0.7831311629},
{"learn":[3.985628919],"iteration":469,"passed_time":0.6928753448,"remaining_time":0.7813275165},
{"learn":[3.985086112],"iteration":470,"passed_time":0.6940417062,"remaining_time":0.7795075639},
{"learn":[3.98466839],"iteration":471,"passed_time":0.6950883173,"remaining_time":0.7775564227},
{"learn":[3.984233894],"iteration":472,"passed_time":0.6967459361,"remaining_time":0.7762898696},
{"learn":[3.981855845],"iteration":473,"passed_time":0.6981051679,"remaining_time":0.7746905449},
{"learn":[3.978684264],"iteration":474,"passed_time":0.6993950404,"remaining_time":0.7730155709},
{"learn":[3.974361269],"iteration":475,"passed_time":0.7004558076,"remaining_time":0.7710900067},
{"learn":[3.972074049],"iteration":476,"passed_time":0.7014252957,"remaining_time":0.7690679867},
{"learn":[3.97191982],"iteration":477,"passed_time":0.7024630026,"remaining_time":0.767124869},
{"learn":[3.969616848],"iteration":478,"passed_time":0.7035927339,"remaining_time":0.765285625},
{"learn":[3.968533527],"iteration":479,"passed_time":0.7045769093,"remaining_time":0.7632916517},
{"learn":[3.967568753],"iteration":480,"passed_time":0.7057717432,"remaining_time":0.7615291782},
{"learn":[3.966232553],"iteration":481,"passed_time":0.7068040039,"remaining_time":0.7595943444},
{"learn":[3.961522393],"iteration":482,"passed_time":0.7080274709,"remaining_time":0.757867914},
{"learn":[3.955829553],"iteration":483,"passed_time":0.7091338299,"remaining_time":0.7560187113},
{"learn":[3.954248095],"iteration":484,"passed_time":0.7100998118,"remaining_time":0.7540235115},
{"learn":[3.951922606],"iteration":485,"passed_time":0.7116310015,"remaining_time":0.7526303185},
{"learn":[3.94978202],"iteration":486,"passed_time":0.7128514481,"remaining_time":0.7509092256},
{"learn":[3.949518999],"iteration":487,"passed_time":0.7138880763,"remaining_time":0.7489973259},
{"learn":[3.945431216],"iteration":488,"passed_time":0.7150421654,"remaining_time":0.7472117515},
{"learn":[3.943249086],"iteration":489,"passed_time":0.7162726951,"remaining_time":0.7455083154},
{"learn":[3.941981548],"iteration":490,"passed_time":0.7174913445,"remaining_time":0.7437944895},
{"learn":[3.936600517],"iteration":491,"passed_time":0.7186368727,"remaining_time":0.7420071775},
{"learn":[3.934476885],"iteration":492,"passed_time":0.7197818123,"remaining_time":0.7402218638},
{"learn":[3.93045798],"iteration":493,"passed_time":0.7209588967,"remaining_time":0.7384720683},
{"learn":[3.925977375],"iteration":494,"passed_time":0.7219987957,"remaining_time":0.73658463},
{"learn":[3.92457993],"iteration":495,"passed_time":0.7233565835,"remaining_time":0.7350236252},
{"learn":[3.919849146],"iteration":496,"passed_time":0.7274772091,"remaining_time":0.7362596301},
{"learn":[3.919681964],"iteration":497,"passed_time":0.7287997524,"remaining_time":0.7346535657},
{"learn":[3.917633027],"iteration":498,"passed_time":0.7298731448,"remaining_time":0.7327984881},
{"learn":[3.916616419],"iteration":499,"passed_time":0.7309557867,"remaining_time":0.7309557867},
{"learn":[3.912896166],"iteration":500,"passed_time":0.7319328127,"remaining_time":0.7290109252},
{"learn":[3.912769674],"iteration":501,"passed_time":0.733082271,"remaining_time":0.727240978},
{"learn":[3.909373788],"iteration":502,"passed_time":0.7343376875,"remaining_time":0.7255781922},
{"learn":[3.906706036],"iteration":503,"passed_time":0.7355870109,"remaining_time":0.7239110266},
{"learn":[3.903895664],"iteration":504,"passed_time":0.7373516542,"remaining_time":0.7227506313},
{"learn":[3.902982967],"iteration":505,"passed_time":0.7386974224,"remaining_time":0.7211789064},
{"learn":[3.900905528],"iteration":506,"passed_time":0.7399613935,"remaining_time":0.7195285346},
{"learn":[3.897463465],"iteration":507,"passed_time":0.740971192,"remaining_time":0.7176335167},
{"learn":[3.895918033],"iteration":508,"passed_time":0.7419580501,"remaining_time":0.7157198479},
{"learn":[3.893921936],"iteration":509,"passed_time":0.7430125364,"remaining_time":0.7138747899},
{"learn":[3.890237934],"iteration":510,"passed_time":0.7440386361,"remaining_time":0.7120056616},
{"learn":[3.887311613],"iteration":511,"passed_time":0.7449416005,"remaining_time":0.710022463},
{"learn":[3.884869735],"iteration":512,"passed_time":0.7460461877,"remaining_time":0.7082348799},
{"learn":[3.882101231],"iteration":513,"passed_time":0.7471807017,"remaining_time":0.706478251},
{"learn":[3.88060368],"iteration":514,"passed_time":0.7485940199,"remaining_time":0.7049866012},
{"learn":[3.877726076],"iteration":515,"passed_time":0.7498599844,"remaining_time":0.7033570397},
{"learn":[3.874938145],"iteration":516,"passed_time":0.751170716,"remaining_time":0.7017707076},
{"learn":[3.874340833],"iteration":517,"passed_time":0.7531149176,"remaining_time":0.7007748848},
{"learn":[3.873105224],"iteration":518,"passed_time":0.7542754776,"remaining_time":0.699049142},
{"learn":[3.869800236],"iteration":519,"passed_time":0.7555866944,"remaining_time":0.697464641},
{"learn":[3.867932518],"iteration":520,"passed_time":0.7565875821,"remaining_time":0.6955958768},
{"learn":[3.866666962],"iteration":521,"passed_time":0.7576364189,"remaining_time":0.6937743453},
{"learn":[3.865527652],"iteration":522,"passed_time":0.7586025691,"remaining_time":0.6918803546},
{"learn":[3.861900081],"iteration":523,"passed_time":0.7595947943,"remaining_time":0.6900135918},
{"learn":[3.858502887],"iteration":524,"passed_time":0.7606024686,"remaining_time":0.6881641382},
{"learn":[3.858335097],"iteration":525,"passed_time":0.7616929053,"remaining_time":0.686392466},
{"learn":[3.855719306],"iteration":526,"passed_time":0.7626617911,"remaining_time":0.6845142831},
{"learn":[3.855137428],"iteration":527,"passed_time":0.7635979519,"remaining_time":0.6826102903},
{"learn":[3.851985706],"iteration":528,"passed_time":0.7646564359,"remaining_time":0.6808188683},
{"learn":[3.851051809],"iteration":529,"passed_time":0.7655872637,"remaining_time":0.6789170075},
{"learn":[3.850679146],"iteration":530,"passed_time":0.7665125912,"remaining_time":0.6770139459},
{"learn":[3.848179484],"iteration":531,"passed_time":0.7675531737,"remaining_time":0.6752159498},
{"learn":[3.844551071],"iteration":532,"passed_time":0.7685393687,"remaining_time":0.6733731429},
{"learn":[3.841604794],"iteration":533,"passed_time":0.7695949555,"remaining_time":0.6715940997},
{"learn":[3.83969656],"iteration":534,"passed_time":0.7705849532,"remaining_time":0.6697607537},
{"learn":[3.836811463],"iteration":535,"passed_time":0.7715940469,"remaining_time":0.6679470854},
{"learn":[3.834182551],"iteration":536,"passed_time":0.7727875259,"remaining_time":0.6662953901},
{"learn":[3.828012842],"iteration":537,"passed_time":0.7739855814,"remaining_time":0.6646493283},
{"learn":[3.826636176],"iteration":538,"passed_time":0.7754562943,"remaining_time":0.6632381293},
{"learn":[3.826189798],"iteration":539,"passed_time":0.7766240423,"remaining_time":0.6615686286},
{"learn":[3.824104738],"iteration":540,"passed_time":0.7778489655,"remaining_time":0.659949492},
{"learn":[3.82300218],"iteration":541,"passed_time":0.7790310809,"remaining_time":0.6582956366},
{"learn":[3.817146402],"iteration":542,"passed_time":0.7801765349,"remaining_time":0.6566126638},
{"learn":[3.814638044],"iteration":543,"passed_time":0.781708658,"remaining_time":0.6552557869},
{"learn":[3.812979573],"iteration":544,"passed_time":0.783434759,"remaining_time":0.6540602116},
{"learn":[3.811938825],"iteration":545,"passed_time":0.7849513318,"remaining_time":0.65268847},
{"learn":[3.811479418],"iteration":546,"passed_time":0.7860662658,"remaining_time":0.6509835803},
{"learn":[3.80742981],"iteration":547,"passed_time":0.7870490563,"remaining_time":0.6491718493},
{"learn":[3.805097043],"iteration":548,"passed_time":0.7881673923,"remaining_time":0.6474744881},
{"learn":[3.801577232],"iteration":549,"passed_time":0.7893011425,"remaining_time":0.6457918439},
{"learn":[3.799762083],"iteration":550,"passed_time":0.790428087,"remaining_time":0.6441056462},
{"learn":[3.796393455],"iteration":551,"passed_time":0.791780206,"remaining_time":0.6426042252},
{"learn":[3.793486459],"iteration":552,"passed_time":0.7928182574,"remaining_time":0.6408494775},
{"learn":[3.792006091],"iteration":553,"passed_time":0.7939390234,"remaining_time":0.6391639069},
{"learn":[3.78932128],"iteration":554,"passed_time":0.7949234574,"remaining_time":0.6373710605},
{"learn":[3.787581812],"iteration":555,"passed_time":0.79590494,"remaining_time":0.6355787651},
{"learn":[3.785308865],"iteration":556,"passed_time":0.7973738411,"remaining_time":0.6341770406},
{"learn":[3.78465475],"iteration":557,"passed_time":0.7983643344,"remaining_time":0.6323961215},
{"learn":[3.780498869],"iteration":558,"passed_time":0.7993759539,"remaining_time":0.6306346971},
{"learn":[3.778734909],"iteration":559,"passed_time":0.8004406251,"remaining_time":0.628917634},
{"learn":[3.778652349],"iteration":560,"passed_time":0.8015718475,"remaining_time":0.6272549751},
{"learn":[3.777928006],"iteration":561,"passed_time":0.8027211963,"remaining_time":0.6256083344},
{"learn":[3.776131406],"iteration":562,"passed_time":0.8039341394,"remaining_time":0.6240128223},
{"learn":[3.772925617],"iteration":563,"passed_time":0.8052190176,"remaining_time":0.622474276},
{"learn":[3.7727745],"iteration":564,"passed_time":0.8064418362,"remaining_time":0.6208888473},
{"learn":[3.771763073],"iteration":565,"passed_time":0.8075532924,"remaining_time":0.619219309},
{"learn":[3.768738162],"iteration":566,"passed_time":0.8086298153,"remaining_time":0.6175250618},
{"learn":[3.767220794],"iteration":567,"passed_time":0.8097942158,"remaining_time":0.6158998261},
{"learn":[3.766691102],"iteration":568,"passed_time":0.8109147407,"remaining_time":0.6142429758},
{"learn":[3.766259335],"iteration":569,"passed_time":0.8125536741,"remaining_time":0.6129790875},
{"learn":[3.76116362],"iteration":570,"passed_time":0.8137529109,"remaining_time":0.6113835355},
{"learn":[3.758633056],"iteration":571,"passed_time":0.8149517628,"remaining_time":0.6097890813},
{"learn":[3.754603809],"iteration":572,"passed_time":0.8161231315,"remaining_time":0.6081755273},
{"learn":[3.754070549],"iteration":573,"passed_time":0.8172224324,"remaining_time":0.6065100282},
{"learn":[3.750534319],"iteration":574,"passed_time":0.8183914316,"remaining_time":0.6048980146},
{"learn":[3.746491516],"iteration":575,"passed_time":0.819544501,"remaining_time":0.6032758132},
{"learn":[3.744210544],"iteration":576,"passed_time":0.8206890329,"remaining_time":0.6016489791},
{"learn":[3.742929991],"iteration":577,"passed_time":0.8216960133,"remaining_time":0.5999233868},
{"learn":[3.740402992],"iteration":578,"passed_time":0.8226650731,"remaining_time":0.5981727043},
{"learn":[3.739644243],"iteration":579,"passed_time":0.8236128312,"remaining_time":0.5964092915},
{"learn":[3.737529404],"iteration":580,"passed_time":0.8246346992,"remaining_time":0.5947021325},
{"learn":[3.737196923],"iteration":581,"passed_time":0.8257209084,"remaining_time":0.593043539},
{"learn":[3.733954464],"iteration":582,"passed_time":0.8271538503,"remaining_time":0.5916349152},
{"learn":[3.731608623],"iteration":583,"passed_time":0.8286607964,"remaining_time":0.5902789234},
{"learn":[3.729843952],"iteration":584,"passed_time":0.8300262866,"remaining_time":0.5888220665},
{"learn":[3.727223798],"iteration":585,"passed_time":0.8310712666,"remaining_time":0.5871390859},
{"learn":[3.725351667],"iteration":586,"passed_time":0.8320300396,"remaining_time":0.5853976258},
{"learn":[3.725026912],"iteration":587,"passed_time":0.8329733268,"remaining_time":0.5836479773},
{"learn":[3.721974565],"iteration":588,"passed_time":0.8340509805,"remaining_time":0.5819948268},
{"learn":[3.720269493],"iteration":589,"passed_time":0.8352895581,"remaining_time":0.5804554556},
{"learn":[3.718907466],"iteration":590,"passed_time":0.8365492346,"remaining_time":0.5789317038},
{"learn":[3.715602912],"iteration":591,"passed_time":0.8377129225,"remaining_time":0.5773426898},
{"learn":[3.714463059],"iteration":592,"passed_time":0.8388310828,"remaining_time":0.5757238629},
{"learn":[3.710802077],"iteration":593,"passed_time":0.8398085428,"remaining_time":0.5740105528},
{"learn":[3.708032435],"iteration":594,"passed_time":0.8407618921,"remaining_time":0.5722833047},
{"learn":[3.703788939],"iteration":595,"passed_time":0.8421573541,"remaining_time":0.5708583407},
{"learn":[3.702500944],"iteration":596,"passed_time":0.8433773197,"remaining_time":0.5693150081},
{"learn":[3.698196925],"iteration":597,"passed_time":0.8446057498,"remaining_time":0.5677784472},
{"learn":[3.69658891],"iteration":598,"passed_time":0.8458338052,"remaining_time":0.5662426642},
{"learn":[3.696124066],"iteration":599,"passed_time":0.8469672871,"remaining_time":0.5646448581},
{"learn":[3.693537052],"iteration":600,"passed_time":0.8481919383,"remaining_time":0.5631091238},
{"learn":[3.691343275],"iteration":601,"passed_time":0.8498644473,"remaining_time":0.561870515},
{"learn":[3.690973831],"iteration":602,"passed_time":0.8513247824,"remaining_time":0.5604907772},
{"learn":[3.686151073],"iteration":603,"passed_time":0.8531312226,"remaining_time":0.559337689},
{"learn":[3.683921982],"iteration":604,"passed_time":0.8542076156,"remaining_time":0.5577057986},
{"learn":[3.679975271],"iteration":605,"passed_time":0.8554161938,"remaining_time":0.5561616837},
{"learn":[3.674047638],"iteration":606,"passed_time":0.8565836419,"remaining_time":0.5545920449},
{"learn":[3.673151794],"iteration":607,"passed_time":0.8581244125,"remaining_time":0.5532644238},
{"learn":[3.670953108],"iteration":608,"passed_time":0.8591373331,"remaining_time":0.551597204},
{"learn":[3.6703947],"iteration":609,"passed_time":0.8602780115,"remaining_time":0.5500138106},
{"learn":[3.668433805],"iteration":610,"passed_time":0.8614207186,"remaining_time":0.548433158},
{"learn":[3.668304956],"iteration":611,"passed_time":0.8625261013,"remaining_time":0.5468302734},
{"learn":[3.667880012],"iteration":612,"passed_time":0.8636752019,"remaining_time":0.5452566119},
{"learn":[3.667282264],"iteration":613,"passed_time":0.8648927891,"remaining_time":0.5437273886},
{"learn":[3.664611483],"iteration":614,"passed_time":0.8661503032,"remaining_time":0.5422241735},
{"learn":[3.662543394],"iteration":615,"passed_time":0.8673529087,"remaining_time":0.5406875275},
{"learn":[3.659041959],"iteration":616,"passed_time":0.8685456562,"remaining_time":0.539145845},
{"learn":[3.656868545],"iteration":617,"passed_time":0.8698179122,"remaining_time":0.5376544376},
{"learn":[3.654785614],"iteration":618,"passed_time":0.8710991713,"remaining_time":0.5361692799},
{"learn":[3.654566096],"iteration":619,"passed_time":0.8725391663,"remaining_time":0.5347820697},
{"learn":[3.651007045],"iteration":620,"passed_time":0.8740703356,"remaining_time":0.5334503336},
{"learn":[3.648921786],"iteration":621,"passed_time":0.8757210317,"remaining_time":0.5321905948},
{"learn":[3.647655706],"iteration":622,"passed_time":0.8775061133,"remaining_time":0.5310109225},
{"learn":[3.647241144],"iteration":623,"passed_time":0.8785221244,"remaining_time":0.5293658955},
{"learn":[3.644195689],"iteration":624,"passed_time":0.8796379015,"remaining_time":0.5277827409},
{"learn":[3.642632246],"iteration":625,"passed_time":0.8807796428,"remaining_time":0.5262165917},
{"learn":[3.642523322],"iteration":626,"passed_time":0.8816592635,"remaining_time":0.5244958617},
{"learn":[3.641494659],"iteration":627,"passed_time":0.8827070016,"remaining_time":0.5228773959},
{"learn":[3.63976496],"iteration":628,"passed_time":0.883707552,"remaining_time":0.5212329122},
{"learn":[3.637945652],"iteration":629,"passed_time":0.8847188932,"remaining_time":0.5195968103},
{"learn":[3.636233667],"iteration":630,"passed_time":0.8856654425,"remaining_time":0.5179247992},
{"learn":[3.635304404],"iteration":631,"passed_time":0.8866138345,"remaining_time":0.5162561568},
{"learn":[3.632234951],"iteration":632,"passed_time":0.8882002989,"remaining_time":0.5149597309},
{"learn":[3.631630987],"iteration":633,"passed_time":0.8897845145,"remaining_time":0.513661092},
{"learn":[3.630301009],"iteration":634,"passed_time":0.8909911576,"remaining_time":0.5121445237},
{"learn":[3.629077964],"iteration":635,"passed_time":0.892144412,"remaining_time":0.5105983742},
{"learn":[3.628004522],"iteration":636,"passed_time":0.8932996369,"remaining_time":0.5090545811},
{"learn":[3.625062876],"iteration":637,"passed_time":0.894314505,"remaining_time":0.5074323681},
{"learn":[3.624917986],"iteration":638,"passed_time":0.8952523744,"remaining_time":0.5057685558},
{"learn":[3.622887087],"iteration":639,"passed_time":0.8962314304,"remaining_time":0.5041301796},
{"learn":[3.621220865],"iteration":640,"passed_time":0.8972689824,"remaining_time":0.502526622},
{"learn":[3.621143844],"iteration":641,"passed_time":0.8982461251,"remaining_time":0.5008911414},
{"learn":[3.620822821],"iteration":642,"passed_time":0.8993553055,"remaining_time":0.4993310172},
{"learn":[3.619202826],"iteration":643,"passed_time":0.9004680887,"remaining_time":0.497774285},
{"learn":[3.618204882],"iteration":644,"passed_time":0.9017489534,"remaining_time":0.4963114394},
{"learn":[3.614259666],"iteration":645,"passed_time":0.9037613026,"remaining_time":0.4952500018},
{"learn":[3.613415661],"iteration":646,"passed_time":0.9049696268,"remaining_time":0.4937469525},
{"learn":[3.611096773],"iteration":647,"passed_time":0.9062721298,"remaining_time":0.4922959718},
{"learn":[3.610820695],"iteration":648,"passed_time":0.9073758199,"remaining_time":0.4907379241},
{"learn":[3.609290065],"iteration":649,"passed_time":0.9084791508,"remaining_time":0.4891810812},
{"learn":[3.60897947],"iteration":650,"passed_time":0.909563921,"remaining_time":0.4876156812},
{"learn":[3.606570702],"iteration":651,"passed_time":0.9105988407,"remaining_time":0.4860251481},
{"learn":[3.606292637],"iteration":652,"passed_time":0.9118168803,"remaining_time":0.4845336255},
{"learn":[3.602753838],"iteration":653,"passed_time":0.9130207569,"remaining_time":0.4830354463},
{"learn":[3.599755869],"iteration":654,"passed_time":0.9142139635,"remaining_time":0.4815325457},
{"learn":[3.599509575],"iteration":655,"passed_time":0.9154575954,"remaining_time":0.4800570317},
{"learn":[3.595337722],"iteration":656,"passed_time":0.9166013209,"remaining_time":0.4785300656},
{"learn":[3.595168561],"iteration":657,"passed_time":0.9184752982,"remaining_time":0.4773838176},
{"learn":[3.59290559],"iteration":658,"passed_time":0.9197828418,"remaining_time":0.4759422596},
{"learn":[3.592015928],"iteration":659,"passed_time":0.9211214477,"remaining_time":0.4745171094},
{"learn":[3.590680403],"iteration":660,"passed_time":0.9221032227,"remaining_time":0.4729092171},
{"learn":[3.590361532],"iteration":661,"passed_time":0.9230491656,"remaining_time":0.4712849214},
{"learn":[3.589069739],"iteration":662,"passed_time":0.92404797,"remaining_time":0.4696895413},
{"learn":[3.585010186],"iteration":663,"passed_time":0.925144207,"remaining_time":0.4681452614},
{"learn":[3.582997552],"iteration":664,"passed_time":0.9262334201,"remaining_time":0.4665987906},
{"learn":[3.582119256],"iteration":665,"passed_time":0.9273030356,"remaining_time":0.4650438647},
{"learn":[3.579019356],"iteration":666,"passed_time":0.9284608591,"remaining_time":0.4635344319},
{"learn":[3.57719559],"iteration":667,"passed_time":0.9294393704,"remaining_time":0.4619369326},
{"learn":[3.574050046],"iteration":668,"passed_time":0.9304828584,"remaining_time":0.4603734322},
{"learn":[3.572204518],"iteration":669,"passed_time":0.9316389913,"remaining_time":0.4588669659},
{"learn":[3.569508025],"iteration":670,"passed_time":0.9332679381,"remaining_time":0.4575933706},
{"learn":[3.566268704],"iteration":671,"passed_time":0.9344887333,"remaining_time":0.4561195008},
{"learn":[3.562564052],"iteration":672,"passed_time":0.9356595127,"remaining_time":0.4546220812},
{"learn":[3.561173586],"iteration":673,"passed_time":0.9367696394,"remaining_time":0.4530962944},
{"learn":[3.559551904],"iteration":674,"passed_time":0.9380312294,"remaining_time":0.451644666},
{"learn":[3.558593054],"iteration":675,"passed_time":0.9390570759,"remaining_time":0.4500806103},
{"learn":[3.555647008],"iteration":676,"passed_time":0.9400420272,"remaining_time":0.4484986333},
{"learn":[3.553100059],"iteration":677,"passed_time":0.9410217021,"remaining_time":0.4469159116},
{"learn":[3.55085578],"iteration":678,"passed_time":0.9420159557,"remaining_time":0.4453418583},
{"learn":[3.550737965],"iteration":679,"passed_time":0.9429706778,"remaining_time":0.4437509072},
{"learn":[3.549408772],"iteration":680,"passed_time":0.9439776848,"remaining_time":0.4421863164},
{"learn":[3.547390589],"iteration":681,"passed_time":0.9450865637,"remaining_time":0.4406708611},
{"learn":[3.54723575],"iteration":682,"passed_time":0.9461172254,"remaining_time":0.4391202935},
{"learn":[3.543988891],"iteration":683,"passed_time":0.9477415328,"remaining_time":0.4378455034},
{"learn":[3.543868508],"iteration":684,"passed_time":0.948738921,"remaining_time":0.4362814016},
{"learn":[3.542752124],"iteration":685,"passed_time":0.9497515342,"remaining_time":0.4347259209},
{"learn":[3.541334315],"iteration":686,"passed_time":0.9507131719,"remaining_time":0.4331487959},
{"learn":[3.540208266],"iteration":687,"passed_time":0.9517064292,"remaining_time":0.4315877993},
{"learn":[3.537730983],"iteration":688,"passed_time":0.9528318076,"remaining_time":0.4300880873},
{"learn":[3.53419867],"iteration":689,"passed_time":0.9539815508,"remaining_time":0.4286004069},
{"learn":[3.532628335],"iteration":690,"passed_time":0.9551420278,"remaining_time":0.4271185045},
{"learn":[3.532204987],"iteration":691,"passed_time":0.9563256418,"remaining_time":0.425647829},
{"learn":[3.530618147],"iteration":692,"passed_time":0.9572978863,"remaining_time":0.424084345},
{"learn":[3.528909306],"iteration":693,"passed_time":0.9582748682,"remaining_time":0.4225246537},
{"learn":[3.526700678],"iteration":694,"passed_time":0.9592582034,"remaining_time":0.4209694274},
{"learn":[3.526439574],"iteration":695,"passed_time":0.9602694388,"remaining_time":0.4194280308},
{"learn":[3.525784216],"iteration":696,"passed_time":0.9613539387,"remaining_time":0.4179200049},
{"learn":[3.524112693],"iteration":697,"passed_time":0.9624770896,"remaining_time":0.4164299156},
{"learn":[3.522813541],"iteration":698,"passed_time":0.9639961885,"remaining_time":0.4151113773},
{"learn":[3.519148203],"iteration":699,"passed_time":0.9655649963,"remaining_time":0.4138135699},
{"learn":[3.517236747],"iteration":700,"passed_time":0.9667912761,"remaining_time":0.4123688895},
{"learn":[3.515603888],"iteration":701,"passed_time":0.9680798895,"remaining_time":0.4109512921},
{"learn":[3.51263524],"iteration":702,"passed_time":0.9693802696,"remaining_time":0.4095390328},
{"learn":[3.51123442],"iteration":703,"passed_time":0.9706013572,"remaining_time":0.4080937525},
{"learn":[3.50828027],"iteration":704,"passed_time":0.9717441198,"remaining_time":0.4066163338},
{"learn":[3.508265537],"iteration":705,"passed_time":0.9724524644,"remaining_time":0.4049589583},
{"learn":[3.506774876],"iteration":706,"passed_time":0.9735563015,"remaining_time":0.4034681702},
{"learn":[3.50552068],"iteration":707,"passed_time":0.9746130287,"remaining_time":0.4019590457},
{"learn":[3.501973993],"iteration":708,"passed_time":0.975583937,"remaining_time":0.4004159741},
{"learn":[3.498880354],"iteration":709,"passed_time":0.9765486069,"remaining_time":0.3988719662},
{"learn":[3.497370959],"iteration":710,"passed_time":0.9780981896,"remaining_time":0.3975673372},
{"learn":[3.496050455],"iteration":711,"passed_time":0.9791194511,"remaining_time":0.3960483173},
{"learn":[3.495630067],"iteration":712,"passed_time":0.980124985,"remaining_time":0.3945243628},
{"learn":[3.49550669],"iteration":713,"passed_time":0.9812574244,"remaining_time":0.3930526938},
{"learn":[3.493652375],"iteration":714,"passed_time":0.9823112572,"remaining_time":0.391550641},
{"learn":[3.491915684],"iteration":715,"passed_time":0.9835310474,"remaining_time":0.3901156668},
{"learn":[3.490303956],"iteration":716,"passed_time":0.9845208493,"remaining_time":0.3885905165},
{"learn":[3.488363853],"iteration":717,"passed_time":0.9855362682,"remaining_time":0.3870769187},
{"learn":[3.485483936],"iteration":718,"passed_time":0.9867521769,"remaining_time":0.3856430622},
{"learn":[3.483763466],"iteration":719,"passed_time":0.9879949307,"remaining_time":0.3842202508},
{"learn":[3.481642352],"iteration":720,"passed_time":0.9892002856,"remaining_time":0.382783467},
{"learn":[3.479826119],"iteration":721,"passed_time":0.9903413376,"remaining_time":0.3813225649},
{"learn":[3.478588728],"iteration":722,"passed_time":0.9914045697,"remaining_time":0.3798327328},
{"learn":[3.475390887],"iteration":723,"passed_time":0.9930646405,"remaining_time":0.3785716033},
{"learn":[3.472636852],"iteration":724,"passed_time":0.9943228997,"remaining_time":0.377156962},
{"learn":[3.47061883],"iteration":725,"passed_time":0.9955835921,"remaining_time":0.3757436698},
{"learn":[3.46953149],"iteration":726,"passed_time":0.9968168821,"remaining_time":0.3743205073},
{"learn":[3.467217162],"iteration":727,"passed_time":0.9980161339,"remaining_time":0.3728851489},
{"learn":[3.465686216],"iteration":728,"passed_time":0.9990935989,"remaining_time":0.371405165},
{"learn":[3.462631216],"iteration":729,"passed_time":1.000377117,"remaining_time":0.3700024952},
{"learn":[3.461451053],"iteration":730,"passed_time":1.001835469,"remaining_time":0.3686644886},
{"learn":[3.458950469],"iteration":731,"passed_time":1.002966605,"remaining_time":0.3672063527},
{"learn":[3.458072145],"iteration":732,"passed_time":1.004027594,"remaining_time":0.3657235573},
{"learn":[3.454364268],"iteration":733,"passed_time":1.005270993,"remaining_time":0.3643080165},
{"learn":[3.453243406],"iteration":734,"passed_time":1.006456046,"remaining_time":0.3628719076},
{"learn":[3.453017963],"iteration":735,"passed_time":1.007999141,"remaining_time":0.3615649092},
{"learn":[3.45201581],"iteration":736,"passed_time":1.009572427,"remaining_time":0.3602680438},
{"learn":[3.449510107],"iteration":737,"passed_time":1.010943007,"remaining_time":0.358898466},
{"learn":[3.447189189],"iteration":738,"passed_time":1.01193711,"remaining_time":0.3573959211},
{"learn":[3.446423605],"iteration":739,"passed_time":1.012871405,"remaining_time":0.3558737369},
{"learn":[3.445531987],"iteration":740,"passed_time":1.013821499,"remaining_time":0.3543586615},
{"learn":[3.445328199],"iteration":741,"passed_time":1.014768076,"remaining_time":0.3528438864},
{"learn":[3.443327544],"iteration":742,"passed_time":1.016439943,"remaining_time":0.3515815146},
{"learn":[3.441475798],"iteration":743,"passed_time":1.017554937,"remaining_time":0.35012643},
{"learn":[3.439046501],"iteration":744,"passed_time":1.018703614,"remaining_time":0.3486837875},
{"learn":[3.435899469],"iteration":745,"passed_time":1.019848251,"remaining_time":0.3472405574},
{"learn":[3.433988352],"iteration":746,"passed_time":1.020849854,"remaining_time":0.3457496827},
{"learn":[3.433413263],"iteration":747,"passed_time":1.021833127,"remaining_time":0.3442539413},
{"learn":[3.429944699],"iteration":748,"passed_time":1.02310655,"remaining_time":0.3428568011},
{"learn":[3.429291634],"iteration":749,"passed_time":1.024311584,"remaining_time":0.3414371948},
{"learn":[3.429175603],"iteration":750,"passed_time":1.025596641,"remaining_time":0.340044692},
{"learn":[3.428780323],"iteration":751,"passed_time":1.026739572,"remaining_time":0.3386056034},
{"learn":[3.423893341],"iteration":752,"passed_time":1.027936116,"remaining_time":0.337184888},
{"learn":[3.421024316],"iteration":753,"passed_time":1.02917079,"remaining_time":0.3357772073},
{"learn":[3.420969872],"iteration":754,"passed_time":1.030150839,"remaining_time":0.3342873583},
{"learn":[3.419544785],"iteration":755,"passed_time":1.031111624,"remaining_time":0.3327926404},
{"learn":[3.417057977],"iteration":756,"passed_time":1.032078181,"remaining_time":0.3313011862},
{"learn":[3.415160245],"iteration":757,"passed_time":1.033083577,"remaining_time":0.3298235168},
{"learn":[3.412854597],"iteration":758,"passed_time":1.034327079,"remaining_time":0.3284226958},
{"learn":[3.410926347],"iteration":759,"passed_time":1.035537648,"remaining_time":0.327011889},
{"learn":[3.408963843],"iteration":760,"passed_time":1.036715714,"remaining_time":0.3255914002},
{"learn":[3.407629634],"iteration":761,"passed_time":1.038461613,"remaining_time":0.3243489029},
{"learn":[3.404384724],"iteration":762,"passed_time":1.039468505,"remaining_time":0.3228755381},
{"learn":[3.403041656],"iteration":763,"passed_time":1.040482897,"remaining_time":0.3214057117},
{"learn":[3.401101731],"iteration":764,"passed_time":1.041476048,"remaining_time":0.3199305506},
{"learn":[3.400890668],"iteration":765,"passed_time":1.042606021,"remaining_time":0.3184984451},
{"learn":[3.399289941],"iteration":766,"passed_time":1.043784242,"remaining_time":0.3170817841},
{"learn":[3.399202366],"iteration":767,"passed_time":1.045658411,"remaining_time":0.3158759784},
{"learn":[3.397447845],"iteration":768,"passed_time":1.046689478,"remaining_time":0.3144151749},
{"learn":[3.394655341],"iteration":769,"passed_time":1.048328279,"remaining_time":0.3131370185},
{"learn":[3.393228229],"iteration":770,"passed_time":1.054318421,"remaining_time":0.3131503482},
{"learn":[3.389691197],"iteration":771,"passed_time":1.056268557,"remaining_time":0.3119549623},
{"learn":[3.389626772],"iteration":772,"passed_time":1.061747496,"remaining_time":0.3117938958},
{"learn":[3.388480222],"iteration":773,"passed_time":1.063551034,"remaining_time":0.3105459092},
{"learn":[3.388215066],"iteration":774,"passed_time":1.065244162,"remaining_time":0.3092644343},
{"learn":[3.386324358],"iteration":775,"passed_time":1.069539848,"remaining_time":0.3087331519},
{"learn":[3.383913061],"iteration":776,"passed_time":1.07102385,"remaining_time":0.3073852235},
{"learn":[3.382839768],"iteration":777,"passed_time":1.072548322,"remaining_time":0.306048493},
{"learn":[3.381961844],"iteration":778,"passed_time":1.073900048,"remaining_time":0.304662273},
{"learn":[3.381521703],"iteration":779,"passed_time":1.075669739,"remaining_time":0.303394029},
{"learn":[3.380918963],"iteration":780,"passed_time":1.077171991,"remaining_time":0.3020495084},
{"learn":[3.377139006],"iteration":781,"passed_time":1.078660845,"remaining_time":0.3007008495},
{"learn":[3.376004372],"iteration":782,"passed_time":1.080392197,"remaining_time":0.2994190379},
{"learn":[3.373826468],"iteration":783,"passed_time":1.082243738,"remaining_time":0.2981691931},
{"learn":[3.373546786],"iteration":784,"passed_time":1.085077071,"remaining_time":0.2971867137},
{"learn":[3.372109181],"iteration":785,"passed_time":1.086904449,"remaining_time":0.2959256388},
{"learn":[3.370764924],"iteration":786,"passed_time":1.088319742,"remaining_time":0.2945515948},
{"learn":[3.367833107],"iteration":787,"passed_time":1.089725447,"remaining_time":0.2931748666},
{"learn":[3.36450404],"iteration":788,"passed_time":1.094364612,"remaining_time":0.2926627795},
{"learn":[3.361794558],"iteration":789,"passed_time":1.095688853,"remaining_time":0.2912590622},
{"learn":[3.356880529],"iteration":790,"passed_time":1.096993567,"remaining_time":0.2898503862},
{"learn":[3.353843509],"iteration":791,"passed_time":1.099161662,"remaining_time":0.2886687192},
{"learn":[3.353640253],"iteration":792,"passed_time":1.102426596,"remaining_time":0.287770877},
{"learn":[3.353055088],"iteration":793,"passed_time":1.104418246,"remaining_time":0.2865367237},
{"learn":[3.351415617],"iteration":794,"passed_time":1.105969928,"remaining_time":0.2851872142},
{"learn":[3.349169061],"iteration":795,"passed_time":1.107510936,"remaining_time":0.2838344609},
{"learn":[3.346211014],"iteration":796,"passed_time":1.110121236,"remaining_time":0.2827535897},
{"learn":[3.344560452],"iteration":797,"passed_time":1.133319625,"remaining_time":0.2868804062},
{"learn":[3.344445461],"iteration":798,"passed_time":1.135321862,"remaining_time":0.2856066261},
{"learn":[3.342608898],"iteration":799,"passed_time":1.137338502,"remaining_time":0.2843346255},
{"learn":[3.339572899],"iteration":800,"passed_time":1.140695808,"remaining_time":0.2833938398},
{"learn":[3.339309302],"iteration":801,"passed_time":1.142224082,"remaining_time":0.2819954716},
{"learn":[3.33698088],"iteration":802,"passed_time":1.14354169,"remaining_time":0.280545097},
{"learn":[3.334746342],"iteration":803,"passed_time":1.144944704,"remaining_time":0.279115873},
{"learn":[3.332048511],"iteration":804,"passed_time":1.146534591,"remaining_time":0.2777319815},
{"learn":[3.331932544],"iteration":805,"passed_time":1.148708968,"remaining_time":0.2764882627},
{"learn":[3.330541133],"iteration":806,"passed_time":1.152079261,"remaining_time":0.2755282495},
{"learn":[3.329124989],"iteration":807,"passed_time":1.153969966,"remaining_time":0.2742106851},
{"learn":[3.32583918],"iteration":808,"passed_time":1.155777723,"remaining_time":0.2728721199},
{"learn":[3.325287299],"iteration":809,"passed_time":1.157611844,"remaining_time":0.2715385806},
{"learn":[3.322745162],"iteration":810,"passed_time":1.159576556,"remaining_time":0.2702342407},
{"learn":[3.319733662],"iteration":811,"passed_time":1.161276893,"remaining_time":0.2688670639},
{"learn":[3.318080007],"iteration":812,"passed_time":1.162584966,"remaining_time":0.2674088421},
{"learn":[3.317179538],"iteration":813,"passed_time":1.165980817,"remaining_time":0.2664280491},
{"learn":[3.315685949],"iteration":814,"passed_time":1.167712378,"remaining_time":0.2650635458},
{"learn":[3.314944576],"iteration":815,"passed_time":1.172992433,"remaining_time":0.2644982938},
{"learn":[3.312369052],"iteration":816,"passed_time":1.174735931,"remaining_time":0.2631293455},
{"learn":[3.312321621],"iteration":817,"passed_time":1.175882316,"remaining_time":0.2616266278},
{"learn":[3.309465776],"iteration":818,"passed_time":1.177958952,"remaining_time":0.2603303667},
{"learn":[3.308307377],"iteration":819,"passed_time":1.186206015,"remaining_time":0.2603866862},
{"learn":[3.308076804],"iteration":820,"passed_time":1.188017296,"remaining_time":0.2590196053},
{"learn":[3.305643326],"iteration":821,"passed_time":1.189439449,"remaining_time":0.2575671799},
{"learn":[3.304154814],"iteration":822,"passed_time":1.190762538,"remaining_time":0.2560935228},
{"learn":[3.303076321],"iteration":823,"passed_time":1.193074262,"remaining_time":0.2548313957},
{"learn":[3.301746372],"iteration":824,"passed_time":1.195225411,"remaining_time":0.2535326629},
{"learn":[3.301345455],"iteration":825,"passed_time":1.196591364,"remaining_time":0.2520664616},
{"learn":[3.299181039],"iteration":826,"passed_time":1.19788033,"remaining_time":0.250584398},
{"learn":[3.297989357],"iteration":827,"passed_time":1.199283484,"remaining_time":0.2491265208},
{"learn":[3.294775182],"iteration":828,"passed_time":1.20242605,"remaining_time":0.2480275688},
{"learn":[3.293840636],"iteration":829,"passed_time":1.206242352,"remaining_time":0.2470616865},
{"learn":[3.289279397],"iteration":830,"passed_time":1.208173434,"remaining_time":0.2457055479},
{"learn":[3.286204979],"iteration":831,"passed_time":1.209977846,"remaining_time":0.2443224497},
{"learn":[3.284833593],"iteration":832,"passed_time":1.212007614,"remaining_time":0.2429835193},
{"learn":[3.283519914],"iteration":833,"passed_time":1.213984803,"remaining_time":0.2416324668},
{"learn":[3.282853026],"iteration":834,"passed_time":1.21587793,"remaining_time":0.2402633036},
{"learn":[3.281944673],"iteration":835,"passed_time":1.218011808,"remaining_time":0.2389401154},
{"learn":[3.279764865],"iteration":836,"passed_time":1.220309396,"remaining_time":0.2376468716},
{"learn":[3.277468839],"iteration":837,"passed_time":1.221840324,"remaining_time":0.2362030221},
{"learn":[3.277124974],"iteration":838,"passed_time":1.224248893,"remaining_time":0.2349273799},
{"learn":[3.275636037],"iteration":839,"passed_time":1.226000791,"remaining_time":0.2335239602},
{"learn":[3.274413635],"iteration":840,"passed_time":1.227367815,"remaining_time":0.2320469472},
{"learn":[3.272636087],"iteration":841,"passed_time":1.22876499,"remaining_time":0.2305758533},
{"learn":[3.269644466],"iteration":842,"passed_time":1.230331416,"remaining_time":0.2291364559},
{"learn":[3.26852083],"iteration":843,"passed_time":1.231773144,"remaining_time":0.2276737091},
{"learn":[3.267820927],"iteration":844,"passed_time":1.234000589,"remaining_time":0.2263551376},
{"learn":[3.267331099],"iteration":845,"passed_time":1.235236921,"remaining_time":0.2248540021},
{"learn":[3.267231014],"iteration":846,"passed_time":1.236610149,"remaining_time":0.2233782206},
{"learn":[3.267158695],"iteration":847,"passed_time":1.240197228,"remaining_time":0.2222995031},
{"learn":[3.264718705],"iteration":848,"passed_time":1.242062293,"remaining_time":0.2209086057},
{"learn":[3.261678512],"iteration":849,"passed_time":1.243388496,"remaining_time":0.2194214993},
{"learn":[3.261368381],"iteration":850,"passed_time":1.244723198,"remaining_time":0.2179362592},
{"learn":[3.260128799],"iteration":851,"passed_time":1.246082701,"remaining_time":0.2164556804},
{"learn":[3.258972952],"iteration":852,"passed_time":1.2482043,"remaining_time":0.2151067199},
{"learn":[3.258724846],"iteration":853,"passed_time":1.250145188,"remaining_time":0.2137250555},
{"learn":[3.25686724],"iteration":854,"passed_time":1.2523956,"remaining_time":0.2123945755},
{"learn":[3.255750259],"iteration":855,"passed_time":1.257111132,"remaining_time":0.211476639},
{"learn":[3.254915866],"iteration":856,"passed_time":1.258618075,"remaining_time":0.2100144513},
{"learn":[3.254348625],"iteration":857,"passed_time":1.26006826,"remaining_time":0.2085427656},
{"learn":[3.253408514],"iteration":858,"passed_time":1.261818539,"remaining_time":0.2071203888},
{"learn":[3.253291714],"iteration":859,"passed_time":1.263298875,"remaining_time":0.2056533052},
{"learn":[3.250186342],"iteration":860,"passed_time":1.265058241,"remaining_time":0.2042312376},
{"learn":[3.249141318],"iteration":861,"passed_time":1.267164027,"remaining_time":0.2028638465},
{"learn":[3.246300388],"iteration":862,"passed_time":1.268880038,"remaining_time":0.2014328681},
{"learn":[3.245205135],"iteration":863,"passed_time":1.27091086,"remaining_time":0.2000507835},
{"learn":[3.244403535],"iteration":864,"passed_time":1.272289214,"remaining_time":0.1985653687},
{"learn":[3.244211781],"iteration":865,"passed_time":1.273704374,"remaining_time":0.1970858962},
{"learn":[3.242286347],"iteration":866,"passed_time":1.275055989,"remaining_time":0.1955968241},
{"learn":[3.239606746],"iteration":867,"passed_time":1.276170409,"remaining_time":0.1940719976},
{"learn":[3.236773361],"iteration":868,"passed_time":1.277358545,"remaining_time":0.1925592282},
{"learn":[3.234552446],"iteration":869,"passed_time":1.279258738,"remaining_time":0.1911536045},
{"learn":[3.233724647],"iteration":870,"passed_time":1.280846009,"remaining_time":0.1897004996},
{"learn":[3.230851485],"iteration":871,"passed_time":1.282844142,"remaining_time":0.188307397},
{"learn":[3.227728941],"iteration":872,"passed_time":1.285543528,"remaining_time":0.1870149233},
{"learn":[3.225787575],"iteration":873,"passed_time":1.287801318,"remaining_time":0.1856555676},
{"learn":[3.222797487],"iteration":874,"passed_time":1.28930839,"remaining_time":0.1841869129},
{"learn":[3.22137014],"iteration":875,"passed_time":1.290670245,"remaining_time":0.1826976146},
{"learn":[3.219701963],"iteration":876,"passed_time":1.292063036,"remaining_time":0.1812129458},
{"learn":[3.21783327],"iteration":877,"passed_time":1.293745815,"remaining_time":0.1797687807},
{"learn":[3.217713355],"iteration":878,"passed_time":1.295825757,"remaining_time":0.1783787447},
{"learn":[3.217666091],"iteration":879,"passed_time":1.297416251,"remaining_time":0.1769203978},
{"learn":[3.214962005],"iteration":880,"passed_time":1.299289206,"remaining_time":0.175499904},
{"learn":[3.214081828],"iteration":881,"passed_time":1.300522066,"remaining_time":0.1739927481},
{"learn":[3.213358337],"iteration":882,"passed_time":1.301813072,"remaining_time":0.1724939177},
{"learn":[3.210850401],"iteration":883,"passed_time":1.303154444,"remaining_time":0.1710021668},
{"learn":[3.207810328],"iteration":884,"passed_time":1.304947693,"remaining_time":0.1695694743},
{"learn":[3.204935073],"iteration":885,"passed_time":1.306316279,"remaining_time":0.168081327},
{"learn":[3.20280198],"iteration":886,"passed_time":1.30759414,"remaining_time":0.1665818916},
{"learn":[3.200663495],"iteration":887,"passed_time":1.308984299,"remaining_time":0.1650971188},
{"learn":[3.197301669],"iteration":888,"passed_time":1.3102995,"remaining_time":0.1636031996},
{"learn":[3.195666943],"iteration":889,"passed_time":1.311465622,"remaining_time":0.1620912566},
{"learn":[3.193886506],"iteration":890,"passed_time":1.3125347,"remaining_time":0.1605682181},
{"learn":[3.190601248],"iteration":891,"passed_time":1.31542777,"remaining_time":0.1592670394},
{"learn":[3.188983797],"iteration":892,"passed_time":1.316833806,"remaining_time":0.1577841178},
{"learn":[3.187365749],"iteration":893,"passed_time":1.318438874,"remaining_time":0.1563249672},
{"learn":[3.186160771],"iteration":894,"passed_time":1.319759875,"remaining_time":0.1548321642},
{"learn":[3.185358981],"iteration":895,"passed_time":1.322379287,"remaining_time":0.153490453},
{"learn":[3.183832164],"iteration":896,"passed_time":1.323879295,"remaining_time":0.1520173549},
{"learn":[3.183106966],"iteration":897,"passed_time":1.325214649,"remaining_time":0.1505254947},
{"learn":[3.182838152],"iteration":898,"passed_time":1.326463266,"remaining_time":0.1490242379},
{"learn":[3.180835453],"iteration":899,"passed_time":1.333750518,"remaining_time":0.148194502},
{"learn":[3.179957348],"iteration":900,"passed_time":1.335549461,"remaining_time":0.146747388},
{"learn":[3.179752966],"iteration":901,"passed_time":1.337243439,"remaining_time":0.1452880898},
{"learn":[3.178851983],"iteration":902,"passed_time":1.339337231,"remaining_time":0.1438712197},
{"learn":[3.176748586],"iteration":903,"passed_time":1.341289878,"remaining_time":0.1424378632},
{"learn":[3.172960988],"iteration":904,"passed_time":1.342434595,"remaining_time":0.1409185486},
{"learn":[3.172794225],"iteration":905,"passed_time":1.343384141,"remaining_time":0.1393798115},
{"learn":[3.169996507],"iteration":906,"passed_time":1.344630734,"remaining_time":0.1378728316},
{"learn":[3.16813015],"iteration":907,"passed_time":1.346136993,"remaining_time":0.1363927349},
{"learn":[3.166920871],"iteration":908,"passed_time":1.347599464,"remaining_time":0.1349081971},
{"learn":[3.16531606],"iteration":909,"passed_time":1.348681299,"remaining_time":0.1333860625},
{"learn":[3.162035247],"iteration":910,"passed_time":1.349706088,"remaining_time":0.1318593214},
{"learn":[3.16189467],"iteration":911,"passed_time":1.350700036,"remaining_time":0.1303307052},
{"learn":[3.161008416],"iteration":912,"passed_time":1.354784186,"remaining_time":0.1290977264},
{"learn":[3.160560787],"iteration":913,"passed_time":1.356742976,"remaining_time":0.1276585295},
{"learn":[3.160416261],"iteration":914,"passed_time":1.358204988,"remaining_time":0.1261720481},
{"learn":[3.15844291],"iteration":915,"passed_time":1.361899926,"remaining_time":0.1248903862},
{"learn":[3.155040501],"iteration":916,"passed_time":1.36313885,"remaining_time":0.1233811609},
{"learn":[3.154937548],"iteration":917,"passed_time":1.364362517,"remaining_time":0.1218711616},
{"learn":[3.153721161],"iteration":918,"passed_time":1.365577202,"remaining_time":0.1203609939},
{"learn":[3.153170511],"iteration":919,"passed_time":1.366841136,"remaining_time":0.118855751},
{"learn":[3.153113601],"iteration":920,"passed_time":1.367792266,"remaining_time":0.1173242009},
{"learn":[3.150607379],"iteration":921,"passed_time":1.36877505,"remaining_time":0.1157965878},
{"learn":[3.148408359],"iteration":922,"passed_time":1.370039944,"remaining_time":0.1142936898},
{"learn":[3.147495728],"iteration":923,"passed_time":1.371191371,"remaining_time":0.1127819742},
{"learn":[3.146946235],"iteration":924,"passed_time":1.372182614,"remaining_time":0.1112580498},
{"learn":[3.14472738],"iteration":925,"passed_time":1.373225497,"remaining_time":0.1097394025},
{"learn":[3.144469477],"iteration":926,"passed_time":1.374352758,"remaining_time":0.1082284264},
{"learn":[3.142975516],"iteration":927,"passed_time":1.386601755,"remaining_time":0.1075811706},
{"learn":[3.14079113],"iteration":928,"passed_time":1.387630251,"remaining_time":0.106051397},
{"learn":[3.138173032],"iteration":929,"passed_time":1.388835367,"remaining_time":0.1045359954},
{"learn":[3.136352813],"iteration":930,"passed_time":1.390251324,"remaining_time":0.1030368865},
{"learn":[3.133735004],"iteration":931,"passed_time":1.392212563,"remaining_time":0.1015777406},
{"learn":[3.1319496],"iteration":932,"passed_time":1.39376487,"remaining_time":0.1000881525},
{"learn":[3.129865343],"iteration":933,"passed_time":1.395001842,"remaining_time":0.09857614727},
{"learn":[3.129830206],"iteration":934,"passed_time":1.395866897,"remaining_time":0.09703887521},
{"learn":[3.126676562],"iteration":935,"passed_time":1.397104703,"remaining_time":0.09552852667},
{"learn":[3.12645665],"iteration":936,"passed_time":1.398514968,"remaining_time":0.09403035535},
{"learn":[3.126378007],"iteration":937,"passed_time":1.399813679,"remaining_time":0.09252499797},
{"learn":[3.124621914],"iteration":938,"passed_time":1.40107098,"remaining_time":0.09101739061},
{"learn":[3.123379018],"iteration":939,"passed_time":1.402477354,"remaining_time":0.08951983112},
{"learn":[3.123332451],"iteration":940,"passed_time":1.403698038,"remaining_time":0.0880108228},
{"learn":[3.122432444],"iteration":941,"passed_time":1.405122059,"remaining_time":0.08651494628},
{"learn":[3.121889006],"iteration":942,"passed_time":1.406820555,"remaining_time":0.08503581295},
{"learn":[3.121070914],"iteration":943,"passed_time":1.407786224,"remaining_time":0.08351274211},
{"learn":[3.118444705],"iteration":944,"passed_time":1.408743122,"remaining_time":0.08199034044},
{"learn":[3.116820458],"iteration":945,"passed_time":1.409759837,"remaining_time":0.08047254886},
{"learn":[3.114971041],"iteration":946,"passed_time":1.410802094,"remaining_time":0.07895724496},
{"learn":[3.114685138],"iteration":947,"passed_time":1.412001694,"remaining_time":0.0774515697},
{"learn":[3.113399363],"iteration":948,"passed_time":1.413236174,"remaining_time":0.07594841398},
{"learn":[3.110575399],"iteration":949,"passed_time":1.414435237,"remaining_time":0.07444395986},
{"learn":[3.110466553],"iteration":950,"passed_time":1.415591726,"remaining_time":0.07293795433},
{"learn":[3.108691641],"iteration":951,"passed_time":1.416805179,"remaining_time":0.07143555524},
{"learn":[3.107898017],"iteration":952,"passed_time":1.417996223,"remaining_time":0.06993265735},
{"learn":[3.105551729],"iteration":953,"passed_time":1.419301866,"remaining_time":0.06843593903},
{"learn":[3.104824945],"iteration":954,"passed_time":1.4204261,"remaining_time":0.06693107277},
{"learn":[3.103186704],"iteration":955,"passed_time":1.422175572,"remaining_time":0.06545577948},
{"learn":[3.102330655],"iteration":956,"passed_time":1.423656148,"remaining_time":0.0639678311},
{"learn":[3.102291298],"iteration":957,"passed_time":1.424930035,"remaining_time":0.06247083661},
{"learn":[3.100363529],"iteration":958,"passed_time":1.425949064,"remaining_time":0.0609634115},
{"learn":[3.097871596],"iteration":959,"passed_time":1.426937124,"remaining_time":0.05945571351},
{"learn":[3.097372213],"iteration":960,"passed_time":1.427886381,"remaining_time":0.05794752222},
{"learn":[3.095981813],"iteration":961,"passed_time":1.428922595,"remaining_time":0.05644392789},
{"learn":[3.095347452],"iteration":962,"passed_time":1.430026564,"remaining_time":0.05494390745},
{"learn":[3.094728409],"iteration":963,"passed_time":1.431315566,"remaining_time":0.05345161863},
{"learn":[3.094118537],"iteration":964,"passed_time":1.432500924,"remaining_time":0.05195599208},
{"learn":[3.093793695],"iteration":965,"passed_time":1.434819713,"remaining_time":0.05050090086},
{"learn":[3.092581602],"iteration":966,"passed_time":1.43592316,"remaining_time":0.04900254838},
{"learn":[3.091694202],"iteration":967,"passed_time":1.437600871,"remaining_time":0.04752399572},
{"learn":[3.090298312],"iteration":968,"passed_time":1.438967689,"remaining_time":0.04603508602},
{"learn":[3.090020107],"iteration":969,"passed_time":1.439890159,"remaining_time":0.04453268534},
{"learn":[3.088949869],"iteration":970,"passed_time":1.440899427,"remaining_time":0.04303407146},
{"learn":[3.086700204],"iteration":971,"passed_time":1.442136652,"remaining_time":0.04154303113},
{"learn":[3.086584317],"iteration":972,"passed_time":1.443326563,"remaining_time":0.04005119959},
{"learn":[3.084850742],"iteration":973,"passed_time":1.444317196,"remaining_time":0.03855466848},
{"learn":[3.084239948],"iteration":974,"passed_time":1.445574558,"remaining_time":0.0370660143},
{"learn":[3.082561673],"iteration":975,"passed_time":1.446746652,"remaining_time":0.03557573735},
{"learn":[3.07991814],"iteration":976,"passed_time":1.447953171,"remaining_time":0.03408692214},
{"learn":[3.079350277],"iteration":977,"passed_time":1.449101942,"remaining_time":0.03259738519},
{"learn":[3.077637462],"iteration":978,"passed_time":1.450163517,"remaining_time":0.03110667402},
{"learn":[3.076733301],"iteration":979,"passed_time":1.45175905,"remaining_time":0.02962773571},
{"learn":[3.07594065],"iteration":980,"passed_time":1.45281915,"remaining_time":0.02813818946},
{"learn":[3.072594655],"iteration":981,"passed_time":1.453816331,"remaining_time":0.02664836452},
{"learn":[3.071977674],"iteration":982,"passed_time":1.454888197,"remaining_time":0.02516083352},
{"learn":[3.069532634],"iteration":983,"passed_time":1.455916697,"remaining_time":0.02367344223},
{"learn":[3.068870784],"iteration":984,"passed_time":1.456875669,"remaining_time":0.02218592389},
{"learn":[3.068801463],"iteration":985,"passed_time":1.45780012,"remaining_time":0.0206989875},
{"learn":[3.067433249],"iteration":986,"passed_time":1.458915845,"remaining_time":0.01921571021},
{"learn":[3.065611456],"iteration":987,"passed_time":1.460001362,"remaining_time":0.01773281006},
{"learn":[3.063039162],"iteration":988,"passed_time":1.461048639,"remaining_time":0.0162502882},
{"learn":[3.06177873],"iteration":989,"passed_time":1.462028251,"remaining_time":0.01476796213},
{"learn":[3.061689148],"iteration":990,"passed_time":1.462944222,"remaining_time":0.01328607265},
{"learn":[3.058984039],"iteration":991,"passed_time":1.463889322,"remaining_time":0.01180555905},
{"learn":[3.057492984],"iteration":992,"passed_time":1.464897805,"remaining_time":0.01032657063},
{"learn":[3.057290731],"iteration":993,"passed_time":1.465965307,"remaining_time":0.008848885155},
{"learn":[3.056068348],"iteration":994,"passed_time":1.467596375,"remaining_time":0.007374856154},
{"learn":[3.054987307],"iteration":995,"passed_time":1.469050435,"remaining_time":0.005899800943},
{"learn":[3.054200234],"iteration":996,"passed_time":1.470474509,"remaining_time":0.004424697619},
{"learn":[3.052732869],"iteration":997,"passed_time":1.471720404,"remaining_time":0.002949339488},
{"learn":[3.051787862],"iteration":998,"passed_time":1.472933809,"remaining_time":0.001474408217},
{"learn":[3.051366222],"iteration":999,"passed_time":1.47421853,"remaining_time":0}
]}